{"upload_date": "20180216", "vcodec": "avc1.4d400b", "extractor": "youtube", "series": null, "chapters": null, "height": 144, "like_count": 11, "duration": 458, "fulltitle": "\u7f8e\u56fd\u4eba\u7684\u5b97\u6559\u4fe1\u4ef0 \u2014 \u8d70\u706b\u5165\u9b54\u7bc7 \uff08\u7ca4\u8bed\uff09", "id": "d3kVU2KV4EQ", "album": null, "view_count": 623, "playlist": "Uploads from Faye Hu", "start_time": null, "title": "\u7f8e\u56fd\u4eba\u7684\u5b97\u6559\u4fe1\u4ef0 \u2014 \u8d70\u706b\u5165\u9b54\u7bc7 \uff08\u7ca4\u8bed\uff09", "_filename": "20180216_NA_d3kVU2KV4EQ.mp4", "creator": null, "is_live": null, "playlist_index": 45, "dislike_count": 2, "playlist_id": "UUheuDxi3s2WAefGCbLHwqAw", "abr": 48, "tags": ["\u7f8e\u56fd", "\u7f8e\u56fd\u4eba", "\u7f8e\u56fd\u4fe1\u4ef0", "\u7f8e\u56fd\u5b97\u6559", "\u7f8e\u56fd\u751f\u6d3b", "\u7f8e\u56fd\u79fb\u6c11", "\u7f8e\u56fd\u98ce\u4fd7", "\u7f8e\u56fd\u4eba\u60c5", "\u7f8e\u56fd\u6559\u4f1a", "\u7f8e\u56fd\u7684\u4e2d\u56fd\u4eba", "\u4e2d\u56fd\u4eba\u5728\u7f8e\u56fd", "\u7f8e\u56fd\u601d\u7ef4", "\u7f8e\u56fd\u601d\u60f3", "\u7f8e\u56fd\u793c\u4eea", "\u7f8e\u56fd\u6587\u5316", "\u7f8e\u56fd\u6587\u5316\u4f20\u7edf", "\u4e2d\u7f8e\u601d\u60f3\u5dee\u5f02", "\u4e2d\u7f8e\u751f\u6d3b\u5dee\u5f02", "\u4e2d\u7f8e\u4fe1\u4ef0\u5dee\u5f02", "\u4e2d\u7f8e\u5b97\u6559\u5dee\u5f02", "\u79fb\u6c11\u7f8e\u56fd"], "uploader_url": "http://www.youtube.com/channel/UCheuDxi3s2WAefGCbLHwqAw", "subtitles": {}, "fps": 30, "stretched_ratio": null, "season_number": null, "annotations": null, "webpage_url_basename": "d3kVU2KV4EQ", "acodec": "mp4a.40.5", "display_id": "d3kVU2KV4EQ", "automatic_captions": {}, "description": "\u6709\u4fe1\u4ef0\u662f\u4e00\u4ef6\u597d\u4e8b\uff0c\u4f46\u4fe1\u5f97\u592a\u8fc7\u5206\u5c31\u4f1a\u53d8\u6210\u201c\u8d70\u706b\u5165\u9b54\u201d\u3002", "format": "160 - 256x144 (DASH video)+139 - audio only (DASH audio)", "track": null, "playlist_uploader": "Faye Hu", "average_rating": null, "uploader": "Faye Hu", "format_id": "160+139", "episode_number": null, "uploader_id": "UCheuDxi3s2WAefGCbLHwqAw", "categories": ["People & Blogs"], "playlist_title": "Uploads from Faye Hu", "thumbnails": [{"url": "https://i.ytimg.com/vi/d3kVU2KV4EQ/hqdefault.jpg", "id": "0"}], "license": null, "artist": null, "extractor_key": "Youtube", "release_date": null, "alt_title": null, "channel_id": null, "thumbnail": "https://i.ytimg.com/vi/d3kVU2KV4EQ/hqdefault.jpg", "vbr": null, "ext": "mp4", "release_year": null, "end_time": null, "webpage_url": "https://www.youtube.com/watch?v=d3kVU2KV4EQ", "formats": [{"asr": 22050, "tbr": 51.052, "protocol": "http_dash_segments", "format": "139 - audio only (DASH audio)", "format_note": "DASH audio", "height": null, "manifest_url": "https://manifest.googlevideo.com/api/manifest/dash/requiressl/yes/source/youtube/id/777915536295e044/itag/0/ei/7aXRXOWnD4mtkgat0ZzwCg/playback_host/r4---sn-a5ms7n7e.googlevideo.com/mm/31%2C26/mn/sn-a5ms7n7e%2Csn-9gv7lnez/ms/au%2Conr/mv/u/pl/21/hfr/all/as/fmp4_audio_clear%2Cwebm_audio_clear%2Cwebm2_audio_clear%2Cfmp4_sd_hd_clear%2Cwebm2_sd_hd_clear/mt/1557242993/fvip/4/ip/155.94.169.201/ipbits/0/expire/1557264973/sparams/ip%2Cipbits%2Cexpire%2Crequiressl%2Csource%2Cid%2Citag%2Cei%2Cplayback_host%2Cmm%2Cmn%2Cms%2Cmv%2Cpl%2Chfr%2Cas/signature/91A46A312F589A77C88E876645AE6A23EB1377B9.9030732EC6AD9C6659B25009A8423C74F9C30BB4/key/yt8", "format_id": "139", "container": "m4a_dash", "language": null, "http_headers": {"Accept-Charset": "ISO-8859-1,utf-8;q=0.7,*;q=0.7", "Accept-Language": "en-us,en;q=0.5", "Accept-Encoding": "gzip, deflate", "Accept": "text/html,application/xhtml+xml,application/xml;q=0.9,*/*;q=0.8", "User-Agent": "Mozilla/5.0 (X11; Linux x86_64; rv:59.0) Gecko/20100101 Firefox/59.0"}, "url": "https://manifest.googlevideo.com/api/manifest/dash/requiressl/yes/source/youtube/id/777915536295e044/itag/0/ei/7aXRXOWnD4mtkgat0ZzwCg/playback_host/r4---sn-a5ms7n7e.googlevideo.com/mm/31%2C26/mn/sn-a5ms7n7e%2Csn-9gv7lnez/ms/au%2Conr/mv/u/pl/21/hfr/all/as/fmp4_audio_clear%2Cwebm_audio_clear%2Cwebm2_audio_clear%2Cfmp4_sd_hd_clear%2Cwebm2_sd_hd_clear/mt/1557242993/fvip/4/ip/155.94.169.201/ipbits/0/expire/1557264973/sparams/ip%2Cipbits%2Cexpire%2Crequiressl%2Csource%2Cid%2Citag%2Cei%2Cplayback_host%2Cmm%2Cmn%2Cms%2Cmv%2Cpl%2Chfr%2Cas/signature/91A46A312F589A77C88E876645AE6A23EB1377B9.9030732EC6AD9C6659B25009A8423C74F9C30BB4/key/yt8", "vcodec": "none", "abr": 48, "width": null, "ext": "m4a", "fragment_base_url": "https://r4---sn-a5ms7n7e.googlevideo.com/videoplayback/id/777915536295e044/itag/139/source/youtube/requiressl/yes/ei/7aXRXOWnD4mtkgat0ZzwCg/mm/31,26/mn/sn-a5ms7n7e,sn-9gv7lnez/ms/au,onr/mv/u/pl/21/ratebypass/yes/mime/audio%2Fmp4/otfp/1/gir/yes/clen/2728744/lmt/1520524361399986/dur/457.804/mt/1557242993/fvip/4/disable_polymer/true/ip/155.94.169.201/ipbits/0/expire/1557264973/sparams/ip,ipbits,expire,id,itag,source,requiressl,ei,mm,mn,ms,mv,pl,ratebypass,mime,otfp,gir,clen,lmt,dur/signature/2F77EDA1B2CF9B2D98BD72B674ECCF5406383010.1D35854C869DCFE0FAFFBECDA6896003F27C4FB7/key/dg_yt0/", "filesize": null, "fps": null, "fragments": [{"path": "range/0-593"}, {"duration": 5.016, "path": "range/1730-32009"}, {"duration": 5.015, "path": "range/32010-61879"}, {"duration": 4.969, "path": "range/61880-91490"}, {"duration": 5.016, "path": "range/91491-121221"}, {"duration": 5.015, "path": "range/121222-151233"}, {"duration": 4.969, "path": "range/151234-180719"}, {"duration": 5.016, "path": "range/180720-210627"}, {"duration": 5.015, "path": "range/210628-240442"}, {"duration": 4.969, "path": "range/240443-270035"}, {"duration": 5.016, "path": "range/270036-299937"}, {"duration": 5.015, "path": "range/299938-329721"}, {"duration": 4.969, "path": "range/329722-359353"}, {"duration": 5.016, "path": "range/359354-389275"}, {"duration": 5.015, "path": "range/389276-419402"}, {"duration": 4.969, "path": "range/419403-448891"}, {"duration": 5.016, "path": "range/448892-478666"}, {"duration": 5.015, "path": "range/478667-508558"}, {"duration": 4.97, "path": "range/508559-538206"}, {"duration": 5.015, "path": "range/538207-567917"}, {"duration": 5.016, "path": "range/567918-597971"}, {"duration": 4.969, "path": "range/597972-627598"}, {"duration": 5.015, "path": "range/627599-657331"}, {"duration": 5.016, "path": "range/657332-687234"}, {"duration": 4.969, "path": "range/687235-716800"}, {"duration": 5.015, "path": "range/716801-746805"}, {"duration": 5.016, "path": "range/746806-776566"}, {"duration": 4.969, "path": "range/776567-805968"}, {"duration": 5.015, "path": "range/805969-836089"}, {"duration": 5.016, "path": "range/836090-865873"}, {"duration": 4.969, "path": "range/865874-895418"}, {"duration": 5.015, "path": "range/895419-925365"}, {"duration": 5.016, "path": "range/925366-955387"}, {"duration": 4.969, "path": "range/955388-984922"}, {"duration": 5.015, "path": "range/984923-1014685"}, {"duration": 5.016, "path": "range/1014686-1044583"}, {"duration": 4.969, "path": "range/1044584-1074324"}, {"duration": 5.016, "path": "range/1074325-1104009"}, {"duration": 5.015, "path": "range/1104010-1133947"}, {"duration": 4.969, "path": "range/1133948-1163607"}, {"duration": 5.016, "path": "range/1163608-1193558"}, {"duration": 5.015, "path": "range/1193559-1223310"}, {"duration": 4.969, "path": "range/1223311-1252881"}, {"duration": 5.016, "path": "range/1252882-1282696"}, {"duration": 5.015, "path": "range/1282697-1312711"}, {"duration": 4.969, "path": "range/1312712-1342163"}, {"duration": 5.016, "path": "range/1342164-1372008"}, {"duration": 5.015, "path": "range/1372009-1402020"}, {"duration": 4.969, "path": "range/1402021-1431571"}, {"duration": 5.016, "path": "range/1431572-1461483"}, {"duration": 5.015, "path": "range/1461484-1491286"}, {"duration": 4.97, "path": "range/1491287-1520981"}, {"duration": 5.015, "path": "range/1520982-1550759"}, {"duration": 5.016, "path": "range/1550760-1580584"}, {"duration": 4.969, "path": "range/1580585-1610269"}, {"duration": 5.015, "path": "range/1610270-1640191"}, {"duration": 5.016, "path": "range/1640192-1670057"}, {"duration": 4.969, "path": "range/1670058-1699691"}, {"duration": 5.015, "path": "range/1699692-1729403"}, {"duration": 5.016, "path": "range/1729404-1759203"}, {"duration": 4.969, "path": "range/1759204-1789041"}, {"duration": 5.015, "path": "range/1789042-1818857"}, {"duration": 5.016, "path": "range/1818858-1848629"}, {"duration": 4.969, "path": "range/1848630-1878241"}, {"duration": 5.015, "path": "range/1878242-1908171"}, {"duration": 5.016, "path": "range/1908172-1937956"}, {"duration": 4.969, "path": "range/1937957-1967622"}, {"duration": 5.015, "path": "range/1967623-1997515"}, {"duration": 5.016, "path": "range/1997516-2027427"}, {"duration": 4.969, "path": "range/2027428-2056958"}, {"duration": 5.016, "path": "range/2056959-2086829"}, {"duration": 5.015, "path": "range/2086830-2116719"}, {"duration": 4.969, "path": "range/2116720-2146266"}, {"duration": 5.016, "path": "range/2146267-2176179"}, {"duration": 5.015, "path": "range/2176180-2206180"}, {"duration": 4.969, "path": "range/2206181-2235557"}, {"duration": 5.016, "path": "range/2235558-2265655"}, {"duration": 5.015, "path": "range/2265656-2295308"}, {"duration": 4.969, "path": "range/2295309-2325049"}, {"duration": 5.016, "path": "range/2325050-2354909"}, {"duration": 5.015, "path": "range/2354910-2384698"}, {"duration": 4.969, "path": "range/2384699-2414449"}, {"duration": 5.016, "path": "range/2414450-2444223"}, {"duration": 5.015, "path": "range/2444224-2474065"}, {"duration": 4.97, "path": "range/2474066-2503525"}, {"duration": 5.015, "path": "range/2503526-2533451"}, {"duration": 5.016, "path": "range/2533452-2563438"}, {"duration": 4.969, "path": "range/2563439-2593022"}, {"duration": 5.015, "path": "range/2593023-2622923"}, {"duration": 5.016, "path": "range/2622924-2652768"}, {"duration": 4.969, "path": "range/2652769-2682314"}, {"duration": 5.015, "path": "range/2682315-2712430"}, {"duration": 2.786, "path": "range/2712431-2728743"}], "acodec": "mp4a.40.5"}, {"asr": 44100, "tbr": 130.06, "protocol": "http_dash_segments", "format": "140 - audio only (DASH audio)", "format_note": "DASH audio", "height": null, "manifest_url": "https://manifest.googlevideo.com/api/manifest/dash/requiressl/yes/source/youtube/id/777915536295e044/itag/0/ei/7aXRXOWnD4mtkgat0ZzwCg/playback_host/r4---sn-a5ms7n7e.googlevideo.com/mm/31%2C26/mn/sn-a5ms7n7e%2Csn-9gv7lnez/ms/au%2Conr/mv/u/pl/21/hfr/all/as/fmp4_audio_clear%2Cwebm_audio_clear%2Cwebm2_audio_clear%2Cfmp4_sd_hd_clear%2Cwebm2_sd_hd_clear/mt/1557242993/fvip/4/ip/155.94.169.201/ipbits/0/expire/1557264973/sparams/ip%2Cipbits%2Cexpire%2Crequiressl%2Csource%2Cid%2Citag%2Cei%2Cplayback_host%2Cmm%2Cmn%2Cms%2Cmv%2Cpl%2Chfr%2Cas/signature/91A46A312F589A77C88E876645AE6A23EB1377B9.9030732EC6AD9C6659B25009A8423C74F9C30BB4/key/yt8", "format_id": "140", "container": "m4a_dash", "language": null, "http_headers": {"Accept-Charset": "ISO-8859-1,utf-8;q=0.7,*;q=0.7", "Accept-Language": "en-us,en;q=0.5", "Accept-Encoding": "gzip, deflate", "Accept": "text/html,application/xhtml+xml,application/xml;q=0.9,*/*;q=0.8", "User-Agent": "Mozilla/5.0 (X11; Linux x86_64; rv:59.0) Gecko/20100101 Firefox/59.0"}, "url": "https://manifest.googlevideo.com/api/manifest/dash/requiressl/yes/source/youtube/id/777915536295e044/itag/0/ei/7aXRXOWnD4mtkgat0ZzwCg/playback_host/r4---sn-a5ms7n7e.googlevideo.com/mm/31%2C26/mn/sn-a5ms7n7e%2Csn-9gv7lnez/ms/au%2Conr/mv/u/pl/21/hfr/all/as/fmp4_audio_clear%2Cwebm_audio_clear%2Cwebm2_audio_clear%2Cfmp4_sd_hd_clear%2Cwebm2_sd_hd_clear/mt/1557242993/fvip/4/ip/155.94.169.201/ipbits/0/expire/1557264973/sparams/ip%2Cipbits%2Cexpire%2Crequiressl%2Csource%2Cid%2Citag%2Cei%2Cplayback_host%2Cmm%2Cmn%2Cms%2Cmv%2Cpl%2Chfr%2Cas/signature/91A46A312F589A77C88E876645AE6A23EB1377B9.9030732EC6AD9C6659B25009A8423C74F9C30BB4/key/yt8", "vcodec": "none", "abr": 128, "width": null, "ext": "m4a", "fragment_base_url": "https://r4---sn-a5ms7n7e.googlevideo.com/videoplayback/id/777915536295e044/itag/140/source/youtube/requiressl/yes/ei/7aXRXOWnD4mtkgat0ZzwCg/mm/31,26/mn/sn-a5ms7n7e,sn-9gv7lnez/ms/au,onr/mv/u/pl/21/ratebypass/yes/mime/audio%2Fmp4/otfp/1/gir/yes/clen/7275981/lmt/1520524361417768/dur/457.711/mt/1557242993/fvip/4/disable_polymer/true/ip/155.94.169.201/ipbits/0/expire/1557264973/sparams/ip,ipbits,expire,id,itag,source,requiressl,ei,mm,mn,ms,mv,pl,ratebypass,mime,otfp,gir,clen,lmt,dur/signature/51232695C6522547BE901398C6A74BBBE6876E47.699E22C65EB6F5D11A70D33DA1C5894AD18A8F10/key/dg_yt0/", "filesize": null, "fps": null, "fragments": [{"path": "range/0-591"}, {"duration": 5.016, "path": "range/1728-81547"}, {"duration": 5.015, "path": "range/81548-160861"}, {"duration": 4.969, "path": "range/160862-240257"}, {"duration": 5.016, "path": "range/240258-319936"}, {"duration": 5.015, "path": "range/319937-399378"}, {"duration": 4.969, "path": "range/399379-479124"}, {"duration": 5.016, "path": "range/479125-558182"}, {"duration": 5.015, "path": "range/558183-637577"}, {"duration": 4.969, "path": "range/637578-717184"}, {"duration": 5.016, "path": "range/717185-796703"}, {"duration": 5.015, "path": "range/796704-876027"}, {"duration": 4.969, "path": "range/876028-955336"}, {"duration": 5.016, "path": "range/955337-1035053"}, {"duration": 5.015, "path": "range/1035054-1114451"}, {"duration": 4.969, "path": "range/1114452-1193921"}, {"duration": 5.016, "path": "range/1193922-1273635"}, {"duration": 5.015, "path": "range/1273636-1352804"}, {"duration": 4.97, "path": "range/1352805-1432026"}, {"duration": 5.015, "path": "range/1432027-1511839"}, {"duration": 5.016, "path": "range/1511840-1591308"}, {"duration": 4.969, "path": "range/1591309-1670486"}, {"duration": 5.015, "path": "range/1670487-1750182"}, {"duration": 5.016, "path": "range/1750183-1829668"}, {"duration": 4.969, "path": "range/1829669-1908890"}, {"duration": 5.015, "path": "range/1908891-1988570"}, {"duration": 5.016, "path": "range/1988571-2067957"}, {"duration": 4.969, "path": "range/2067958-2147261"}, {"duration": 5.015, "path": "range/2147262-2226944"}, {"duration": 5.016, "path": "range/2226945-2306288"}, {"duration": 4.969, "path": "range/2306289-2385672"}, {"duration": 5.015, "path": "range/2385673-2465391"}, {"duration": 5.016, "path": "range/2465392-2544753"}, {"duration": 4.969, "path": "range/2544754-2624259"}, {"duration": 5.015, "path": "range/2624260-2703805"}, {"duration": 5.016, "path": "range/2703806-2783178"}, {"duration": 4.969, "path": "range/2783179-2862491"}, {"duration": 5.016, "path": "range/2862492-2942134"}, {"duration": 5.015, "path": "range/2942135-3021525"}, {"duration": 4.969, "path": "range/3021526-3100923"}, {"duration": 5.016, "path": "range/3100924-3180346"}, {"duration": 5.015, "path": "range/3180347-3259852"}, {"duration": 4.969, "path": "range/3259853-3339142"}, {"duration": 5.016, "path": "range/3339143-3418933"}, {"duration": 5.015, "path": "range/3418934-3498352"}, {"duration": 4.969, "path": "range/3498353-3577534"}, {"duration": 5.016, "path": "range/3577535-3657147"}, {"duration": 5.015, "path": "range/3657148-3736600"}, {"duration": 4.969, "path": "range/3736601-3815860"}, {"duration": 5.016, "path": "range/3815861-3895758"}, {"duration": 5.015, "path": "range/3895759-3974907"}, {"duration": 4.97, "path": "range/3974908-4054267"}, {"duration": 5.015, "path": "range/4054268-4134175"}, {"duration": 5.016, "path": "range/4134176-4213207"}, {"duration": 4.969, "path": "range/4213208-4292648"}, {"duration": 5.015, "path": "range/4292649-4372387"}, {"duration": 5.016, "path": "range/4372388-4451782"}, {"duration": 4.969, "path": "range/4451783-4531041"}, {"duration": 5.015, "path": "range/4531042-4610741"}, {"duration": 5.016, "path": "range/4610742-4689967"}, {"duration": 4.969, "path": "range/4689968-4769379"}, {"duration": 5.015, "path": "range/4769380-4849168"}, {"duration": 5.016, "path": "range/4849169-4928421"}, {"duration": 4.969, "path": "range/4928422-5007714"}, {"duration": 5.015, "path": "range/5007715-5087433"}, {"duration": 5.016, "path": "range/5087434-5166831"}, {"duration": 4.969, "path": "range/5166832-5246205"}, {"duration": 5.015, "path": "range/5246206-5325823"}, {"duration": 5.016, "path": "range/5325824-5405297"}, {"duration": 4.969, "path": "range/5405298-5484495"}, {"duration": 5.016, "path": "range/5484496-5564260"}, {"duration": 5.015, "path": "range/5564261-5643555"}, {"duration": 4.969, "path": "range/5643556-5722855"}, {"duration": 5.016, "path": "range/5722856-5802574"}, {"duration": 5.015, "path": "range/5802575-5881878"}, {"duration": 4.969, "path": "range/5881879-5961341"}, {"duration": 5.016, "path": "range/5961342-6040988"}, {"duration": 5.015, "path": "range/6040989-6120260"}, {"duration": 4.969, "path": "range/6120261-6199599"}, {"duration": 5.016, "path": "range/6199600-6279321"}, {"duration": 5.015, "path": "range/6279322-6358650"}, {"duration": 4.969, "path": "range/6358651-6438035"}, {"duration": 5.016, "path": "range/6438036-6517716"}, {"duration": 5.015, "path": "range/6517717-6597096"}, {"duration": 4.97, "path": "range/6597097-6676239"}, {"duration": 5.015, "path": "range/6676240-6756052"}, {"duration": 5.016, "path": "range/6756053-6835279"}, {"duration": 4.969, "path": "range/6835280-6914705"}, {"duration": 5.015, "path": "range/6914706-6994608"}, {"duration": 5.016, "path": "range/6994609-7073787"}, {"duration": 4.969, "path": "range/7073788-7152992"}, {"duration": 5.015, "path": "range/7152993-7232882"}, {"duration": 2.786, "path": "range/7232883-7275980"}], "acodec": "mp4a.40.2"}, {"asr": null, "tbr": 98.31, "protocol": "http_dash_segments", "format": "278 - 256x144 (DASH video)", "format_note": "DASH video", "height": 144, "manifest_url": "https://manifest.googlevideo.com/api/manifest/dash/requiressl/yes/source/youtube/id/777915536295e044/itag/0/ei/7aXRXOWnD4mtkgat0ZzwCg/playback_host/r4---sn-a5ms7n7e.googlevideo.com/mm/31%2C26/mn/sn-a5ms7n7e%2Csn-9gv7lnez/ms/au%2Conr/mv/u/pl/21/hfr/all/as/fmp4_audio_clear%2Cwebm_audio_clear%2Cwebm2_audio_clear%2Cfmp4_sd_hd_clear%2Cwebm2_sd_hd_clear/mt/1557242993/fvip/4/ip/155.94.169.201/ipbits/0/expire/1557264973/sparams/ip%2Cipbits%2Cexpire%2Crequiressl%2Csource%2Cid%2Citag%2Cei%2Cplayback_host%2Cmm%2Cmn%2Cms%2Cmv%2Cpl%2Chfr%2Cas/signature/91A46A312F589A77C88E876645AE6A23EB1377B9.9030732EC6AD9C6659B25009A8423C74F9C30BB4/key/yt8", "format_id": "278", "container": "webm_dash", "language": null, "http_headers": {"Accept-Charset": "ISO-8859-1,utf-8;q=0.7,*;q=0.7", "Accept-Language": "en-us,en;q=0.5", "Accept-Encoding": "gzip, deflate", "Accept": "text/html,application/xhtml+xml,application/xml;q=0.9,*/*;q=0.8", "User-Agent": "Mozilla/5.0 (X11; Linux x86_64; rv:59.0) Gecko/20100101 Firefox/59.0"}, "url": "https://manifest.googlevideo.com/api/manifest/dash/requiressl/yes/source/youtube/id/777915536295e044/itag/0/ei/7aXRXOWnD4mtkgat0ZzwCg/playback_host/r4---sn-a5ms7n7e.googlevideo.com/mm/31%2C26/mn/sn-a5ms7n7e%2Csn-9gv7lnez/ms/au%2Conr/mv/u/pl/21/hfr/all/as/fmp4_audio_clear%2Cwebm_audio_clear%2Cwebm2_audio_clear%2Cfmp4_sd_hd_clear%2Cwebm2_sd_hd_clear/mt/1557242993/fvip/4/ip/155.94.169.201/ipbits/0/expire/1557264973/sparams/ip%2Cipbits%2Cexpire%2Crequiressl%2Csource%2Cid%2Citag%2Cei%2Cplayback_host%2Cmm%2Cmn%2Cms%2Cmv%2Cpl%2Chfr%2Cas/signature/91A46A312F589A77C88E876645AE6A23EB1377B9.9030732EC6AD9C6659B25009A8423C74F9C30BB4/key/yt8", "vcodec": "vp9", "width": 256, "ext": "webm", "fragment_base_url": "https://r4---sn-a5ms7n7e.googlevideo.com/videoplayback/id/777915536295e044/itag/278/source/youtube/requiressl/yes/ei/7aXRXOWnD4mtkgat0ZzwCg/mm/31,26/mn/sn-a5ms7n7e,sn-9gv7lnez/ms/au,onr/mv/u/pl/21/ratebypass/yes/mime/video%2Fwebm/otfp/1/gir/yes/clen/5479187/lmt/1520585050783892/dur/457.657/mt/1557242993/fvip/4/disable_polymer/true/ip/155.94.169.201/ipbits/0/expire/1557264973/sparams/ip,ipbits,expire,id,itag,source,requiressl,ei,mm,mn,ms,mv,pl,ratebypass,mime,otfp,gir,clen,lmt,dur/signature/855F985B7C6466843FCB367106CC32F6AF4AA32C.1746ACACB4363A50CD84AB7F87EB1CF12EE54C92/key/dg_yt0/", "filesize": null, "fps": 30, "fragments": [{"path": "range/0-218"}, {"duration": 5.339, "path": "range/1671-65428"}, {"duration": 5.338, "path": "range/65429-130050"}, {"duration": 5.339, "path": "range/130051-194046"}, {"duration": 5.339, "path": "range/194047-251476"}, {"duration": 5.338, "path": "range/251477-315865"}, {"duration": 5.339, "path": "range/315866-380345"}, {"duration": 5.339, "path": "range/380346-444144"}, {"duration": 5.338, "path": "range/444145-508262"}, {"duration": 5.339, "path": "range/508263-571815"}, {"duration": 5.339, "path": "range/571816-635894"}, {"duration": 5.338, "path": "range/635895-698359"}, {"duration": 5.339, "path": "range/698360-763099"}, {"duration": 5.339, "path": "range/763100-828574"}, {"duration": 5.338, "path": "range/828575-893316"}, {"duration": 5.339, "path": "range/893317-956843"}, {"duration": 5.339, "path": "range/956844-1021006"}, {"duration": 5.338, "path": "range/1021007-1083066"}, {"duration": 5.339, "path": "range/1083067-1148676"}, {"duration": 5.339, "path": "range/1148677-1213110"}, {"duration": 5.338, "path": "range/1213111-1277718"}, {"duration": 5.339, "path": "range/1277719-1342279"}, {"duration": 5.339, "path": "range/1342280-1407532"}, {"duration": 5.338, "path": "range/1407533-1470227"}, {"duration": 5.339, "path": "range/1470228-1534587"}, {"duration": 5.339, "path": "range/1534588-1595975"}, {"duration": 5.338, "path": "range/1595976-1659116"}, {"duration": 5.339, "path": "range/1659117-1721187"}, {"duration": 5.339, "path": "range/1721188-1784266"}, {"duration": 5.338, "path": "range/1784267-1849212"}, {"duration": 5.339, "path": "range/1849213-1912268"}, {"duration": 5.339, "path": "range/1912269-1974449"}, {"duration": 5.338, "path": "range/1974450-2038959"}, {"duration": 5.339, "path": "range/2038960-2099835"}, {"duration": 5.339, "path": "range/2099836-2162952"}, {"duration": 5.338, "path": "range/2162953-2226455"}, {"duration": 5.339, "path": "range/2226456-2289376"}, {"duration": 5.339, "path": "range/2289377-2349247"}, {"duration": 5.338, "path": "range/2349248-2414058"}, {"duration": 5.339, "path": "range/2414059-2477946"}, {"duration": 5.339, "path": "range/2477947-2542494"}, {"duration": 5.338, "path": "range/2542495-2606154"}, {"duration": 5.339, "path": "range/2606155-2669692"}, {"duration": 5.339, "path": "range/2669693-2733888"}, {"duration": 5.338, "path": "range/2733889-2797057"}, {"duration": 5.339, "path": "range/2797058-2861457"}, {"duration": 5.339, "path": "range/2861458-2925672"}, {"duration": 5.338, "path": "range/2925673-2990726"}, {"duration": 5.339, "path": "range/2990727-3055657"}, {"duration": 5.339, "path": "range/3055658-3119746"}, {"duration": 5.338, "path": "range/3119747-3183755"}, {"duration": 5.339, "path": "range/3183756-3247388"}, {"duration": 5.339, "path": "range/3247389-3312078"}, {"duration": 5.338, "path": "range/3312079-3375808"}, {"duration": 5.339, "path": "range/3375809-3440625"}, {"duration": 5.339, "path": "range/3440626-3505563"}, {"duration": 5.338, "path": "range/3505564-3569337"}, {"duration": 5.339, "path": "range/3569338-3634138"}, {"duration": 5.339, "path": "range/3634139-3698868"}, {"duration": 5.338, "path": "range/3698869-3762827"}, {"duration": 5.339, "path": "range/3762828-3826330"}, {"duration": 5.339, "path": "range/3826331-3890834"}, {"duration": 5.338, "path": "range/3890835-3955831"}, {"duration": 5.339, "path": "range/3955832-4019333"}, {"duration": 5.339, "path": "range/4019334-4083936"}, {"duration": 5.338, "path": "range/4083937-4147469"}, {"duration": 5.339, "path": "range/4147470-4211140"}, {"duration": 5.339, "path": "range/4211141-4276017"}, {"duration": 5.338, "path": "range/4276018-4339847"}, {"duration": 5.339, "path": "range/4339848-4403151"}, {"duration": 5.339, "path": "range/4403152-4467219"}, {"duration": 5.338, "path": "range/4467220-4531508"}, {"duration": 5.339, "path": "range/4531509-4596695"}, {"duration": 5.339, "path": "range/4596696-4661035"}, {"duration": 5.338, "path": "range/4661036-4725329"}, {"duration": 5.339, "path": "range/4725330-4789853"}, {"duration": 5.339, "path": "range/4789854-4854312"}, {"duration": 5.338, "path": "range/4854313-4918705"}, {"duration": 5.339, "path": "range/4918706-4982128"}, {"duration": 5.339, "path": "range/4982129-5046863"}, {"duration": 5.338, "path": "range/5046864-5111200"}, {"duration": 5.339, "path": "range/5111201-5175381"}, {"duration": 5.339, "path": "range/5175382-5239346"}, {"duration": 5.338, "path": "range/5239347-5304043"}, {"duration": 5.339, "path": "range/5304044-5367821"}, {"duration": 5.339, "path": "range/5367822-5432083"}, {"duration": 3.87, "path": "range/5432084-5479186"}], "acodec": "none"}, {"asr": null, "tbr": 108.0, "protocol": "http_dash_segments", "format": "160 - 256x144 (DASH video)", "format_note": "DASH video", "height": 144, "manifest_url": "https://manifest.googlevideo.com/api/manifest/dash/requiressl/yes/source/youtube/id/777915536295e044/itag/0/ei/7aXRXOWnD4mtkgat0ZzwCg/playback_host/r4---sn-a5ms7n7e.googlevideo.com/mm/31%2C26/mn/sn-a5ms7n7e%2Csn-9gv7lnez/ms/au%2Conr/mv/u/pl/21/hfr/all/as/fmp4_audio_clear%2Cwebm_audio_clear%2Cwebm2_audio_clear%2Cfmp4_sd_hd_clear%2Cwebm2_sd_hd_clear/mt/1557242993/fvip/4/ip/155.94.169.201/ipbits/0/expire/1557264973/sparams/ip%2Cipbits%2Cexpire%2Crequiressl%2Csource%2Cid%2Citag%2Cei%2Cplayback_host%2Cmm%2Cmn%2Cms%2Cmv%2Cpl%2Chfr%2Cas/signature/91A46A312F589A77C88E876645AE6A23EB1377B9.9030732EC6AD9C6659B25009A8423C74F9C30BB4/key/yt8", "format_id": "160", "container": "mp4_dash", "language": null, "http_headers": {"Accept-Charset": "ISO-8859-1,utf-8;q=0.7,*;q=0.7", "Accept-Language": "en-us,en;q=0.5", "Accept-Encoding": "gzip, deflate", "Accept": "text/html,application/xhtml+xml,application/xml;q=0.9,*/*;q=0.8", "User-Agent": "Mozilla/5.0 (X11; Linux x86_64; rv:59.0) Gecko/20100101 Firefox/59.0"}, "url": "https://manifest.googlevideo.com/api/manifest/dash/requiressl/yes/source/youtube/id/777915536295e044/itag/0/ei/7aXRXOWnD4mtkgat0ZzwCg/playback_host/r4---sn-a5ms7n7e.googlevideo.com/mm/31%2C26/mn/sn-a5ms7n7e%2Csn-9gv7lnez/ms/au%2Conr/mv/u/pl/21/hfr/all/as/fmp4_audio_clear%2Cwebm_audio_clear%2Cwebm2_audio_clear%2Cfmp4_sd_hd_clear%2Cwebm2_sd_hd_clear/mt/1557242993/fvip/4/ip/155.94.169.201/ipbits/0/expire/1557264973/sparams/ip%2Cipbits%2Cexpire%2Crequiressl%2Csource%2Cid%2Citag%2Cei%2Cplayback_host%2Cmm%2Cmn%2Cms%2Cmv%2Cpl%2Chfr%2Cas/signature/91A46A312F589A77C88E876645AE6A23EB1377B9.9030732EC6AD9C6659B25009A8423C74F9C30BB4/key/yt8", "vcodec": "avc1.4d400b", "width": 256, "ext": "mp4", "fragment_base_url": "https://r4---sn-a5ms7n7e.googlevideo.com/videoplayback/id/777915536295e044/itag/160/source/yt_otf/requiressl/yes/ei/7aXRXOWnD4mtkgat0ZzwCg/mm/31,26/mn/sn-a5ms7n7e,sn-9gv7lnez/ms/au,onr/mv/u/pl/21/ratebypass/yes/mime/video%2Fmp4/otfp/1/otf/1/lmt/1520524473015680/mt/1557242993/fvip/4/disable_polymer/true/ip/155.94.169.201/ipbits/0/expire/1557264973/sparams/ip,ipbits,expire,id,itag,source,requiressl,ei,mm,mn,ms,mv,pl,ratebypass,mime,otfp,otf,lmt/signature/6C4CF90D821F9D7F3895EB27F78CB6888378B50F.6884A97C56223C326A3ECBC0BE9A9A1775C9DD14/key/dg_yt0/", "filesize": null, "fps": 30, "fragments": [{"path": "sq/0"}, {"duration": 5.339, "path": "sq/1/dur/5.339"}, {"duration": 5.338, "path": "sq/2/dur/5.338"}, {"duration": 5.339, "path": "sq/3/dur/5.339"}, {"duration": 5.339, "path": "sq/4/dur/5.339"}, {"duration": 5.338, "path": "sq/5/dur/5.338"}, {"duration": 5.339, "path": "sq/6/dur/5.339"}, {"duration": 5.339, "path": "sq/7/dur/5.339"}, {"duration": 5.338, "path": "sq/8/dur/5.338"}, {"duration": 5.339, "path": "sq/9/dur/5.339"}, {"duration": 5.339, "path": "sq/10/dur/5.339"}, {"duration": 5.338, "path": "sq/11/dur/5.338"}, {"duration": 5.339, "path": "sq/12/dur/5.339"}, {"duration": 5.339, "path": "sq/13/dur/5.339"}, {"duration": 5.338, "path": "sq/14/dur/5.338"}, {"duration": 5.339, "path": "sq/15/dur/5.339"}, {"duration": 5.339, "path": "sq/16/dur/5.339"}, {"duration": 5.338, "path": "sq/17/dur/5.338"}, {"duration": 5.339, "path": "sq/18/dur/5.339"}, {"duration": 5.339, "path": "sq/19/dur/5.339"}, {"duration": 5.338, "path": "sq/20/dur/5.338"}, {"duration": 5.339, "path": "sq/21/dur/5.339"}, {"duration": 5.339, "path": "sq/22/dur/5.339"}, {"duration": 5.338, "path": "sq/23/dur/5.338"}, {"duration": 5.339, "path": "sq/24/dur/5.339"}, {"duration": 5.339, "path": "sq/25/dur/5.339"}, {"duration": 5.338, "path": "sq/26/dur/5.338"}, {"duration": 5.339, "path": "sq/27/dur/5.339"}, {"duration": 5.339, "path": "sq/28/dur/5.339"}, {"duration": 5.338, "path": "sq/29/dur/5.338"}, {"duration": 5.339, "path": "sq/30/dur/5.339"}, {"duration": 5.339, "path": "sq/31/dur/5.339"}, {"duration": 5.338, "path": "sq/32/dur/5.338"}, {"duration": 5.339, "path": "sq/33/dur/5.339"}, {"duration": 5.339, "path": "sq/34/dur/5.339"}, {"duration": 5.338, "path": "sq/35/dur/5.338"}, {"duration": 5.339, "path": "sq/36/dur/5.339"}, {"duration": 5.339, "path": "sq/37/dur/5.339"}, {"duration": 5.338, "path": "sq/38/dur/5.338"}, {"duration": 5.339, "path": "sq/39/dur/5.339"}, {"duration": 5.339, "path": "sq/40/dur/5.339"}, {"duration": 5.338, "path": "sq/41/dur/5.338"}, {"duration": 5.339, "path": "sq/42/dur/5.339"}, {"duration": 5.339, "path": "sq/43/dur/5.339"}, {"duration": 5.338, "path": "sq/44/dur/5.338"}, {"duration": 5.339, "path": "sq/45/dur/5.339"}, {"duration": 5.339, "path": "sq/46/dur/5.339"}, {"duration": 5.338, "path": "sq/47/dur/5.338"}, {"duration": 5.339, "path": "sq/48/dur/5.339"}, {"duration": 5.339, "path": "sq/49/dur/5.339"}, {"duration": 5.338, "path": "sq/50/dur/5.338"}, {"duration": 5.339, "path": "sq/51/dur/5.339"}, {"duration": 5.339, "path": "sq/52/dur/5.339"}, {"duration": 5.338, "path": "sq/53/dur/5.338"}, {"duration": 5.339, "path": "sq/54/dur/5.339"}, {"duration": 5.339, "path": "sq/55/dur/5.339"}, {"duration": 5.338, "path": "sq/56/dur/5.338"}, {"duration": 5.339, "path": "sq/57/dur/5.339"}, {"duration": 5.339, "path": "sq/58/dur/5.339"}, {"duration": 5.338, "path": "sq/59/dur/5.338"}, {"duration": 5.339, "path": "sq/60/dur/5.339"}, {"duration": 5.339, "path": "sq/61/dur/5.339"}, {"duration": 5.338, "path": "sq/62/dur/5.338"}, {"duration": 5.339, "path": "sq/63/dur/5.339"}, {"duration": 5.339, "path": "sq/64/dur/5.339"}, {"duration": 5.338, "path": "sq/65/dur/5.338"}, {"duration": 5.339, "path": "sq/66/dur/5.339"}, {"duration": 5.339, "path": "sq/67/dur/5.339"}, {"duration": 5.338, "path": "sq/68/dur/5.338"}, {"duration": 5.339, "path": "sq/69/dur/5.339"}, {"duration": 5.339, "path": "sq/70/dur/5.339"}, {"duration": 5.338, "path": "sq/71/dur/5.338"}, {"duration": 5.339, "path": "sq/72/dur/5.339"}, {"duration": 5.339, "path": "sq/73/dur/5.339"}, {"duration": 5.338, "path": "sq/74/dur/5.338"}, {"duration": 5.339, "path": "sq/75/dur/5.339"}, {"duration": 5.339, "path": "sq/76/dur/5.339"}, {"duration": 5.338, "path": "sq/77/dur/5.338"}, {"duration": 5.339, "path": "sq/78/dur/5.339"}, {"duration": 5.339, "path": "sq/79/dur/5.339"}, {"duration": 5.338, "path": "sq/80/dur/5.338"}, {"duration": 5.339, "path": "sq/81/dur/5.339"}, {"duration": 5.339, "path": "sq/82/dur/5.339"}, {"duration": 5.338, "path": "sq/83/dur/5.338"}, {"duration": 5.339, "path": "sq/84/dur/5.339"}, {"duration": 5.339, "path": "sq/85/dur/5.339"}, {"duration": 3.871, "path": "sq/86/dur/3.871"}], "acodec": "none"}, {"asr": null, "tbr": 228.852, "protocol": "http_dash_segments", "format": "242 - 426x240 (DASH video)", "format_note": "DASH video", "height": 240, "manifest_url": "https://manifest.googlevideo.com/api/manifest/dash/requiressl/yes/source/youtube/id/777915536295e044/itag/0/ei/7aXRXOWnD4mtkgat0ZzwCg/playback_host/r4---sn-a5ms7n7e.googlevideo.com/mm/31%2C26/mn/sn-a5ms7n7e%2Csn-9gv7lnez/ms/au%2Conr/mv/u/pl/21/hfr/all/as/fmp4_audio_clear%2Cwebm_audio_clear%2Cwebm2_audio_clear%2Cfmp4_sd_hd_clear%2Cwebm2_sd_hd_clear/mt/1557242993/fvip/4/ip/155.94.169.201/ipbits/0/expire/1557264973/sparams/ip%2Cipbits%2Cexpire%2Crequiressl%2Csource%2Cid%2Citag%2Cei%2Cplayback_host%2Cmm%2Cmn%2Cms%2Cmv%2Cpl%2Chfr%2Cas/signature/91A46A312F589A77C88E876645AE6A23EB1377B9.9030732EC6AD9C6659B25009A8423C74F9C30BB4/key/yt8", "format_id": "242", "container": "webm_dash", "language": null, "http_headers": {"Accept-Charset": "ISO-8859-1,utf-8;q=0.7,*;q=0.7", "Accept-Language": "en-us,en;q=0.5", "Accept-Encoding": "gzip, deflate", "Accept": "text/html,application/xhtml+xml,application/xml;q=0.9,*/*;q=0.8", "User-Agent": "Mozilla/5.0 (X11; Linux x86_64; rv:59.0) Gecko/20100101 Firefox/59.0"}, "url": "https://manifest.googlevideo.com/api/manifest/dash/requiressl/yes/source/youtube/id/777915536295e044/itag/0/ei/7aXRXOWnD4mtkgat0ZzwCg/playback_host/r4---sn-a5ms7n7e.googlevideo.com/mm/31%2C26/mn/sn-a5ms7n7e%2Csn-9gv7lnez/ms/au%2Conr/mv/u/pl/21/hfr/all/as/fmp4_audio_clear%2Cwebm_audio_clear%2Cwebm2_audio_clear%2Cfmp4_sd_hd_clear%2Cwebm2_sd_hd_clear/mt/1557242993/fvip/4/ip/155.94.169.201/ipbits/0/expire/1557264973/sparams/ip%2Cipbits%2Cexpire%2Crequiressl%2Csource%2Cid%2Citag%2Cei%2Cplayback_host%2Cmm%2Cmn%2Cms%2Cmv%2Cpl%2Chfr%2Cas/signature/91A46A312F589A77C88E876645AE6A23EB1377B9.9030732EC6AD9C6659B25009A8423C74F9C30BB4/key/yt8", "vcodec": "vp9", "width": 426, "ext": "webm", "fragment_base_url": "https://r4---sn-a5ms7n7e.googlevideo.com/videoplayback/id/777915536295e044/itag/242/source/youtube/requiressl/yes/ei/7aXRXOWnD4mtkgat0ZzwCg/mm/31,26/mn/sn-a5ms7n7e,sn-9gv7lnez/ms/au,onr/mv/u/pl/21/ratebypass/yes/mime/video%2Fwebm/otfp/1/gir/yes/clen/11797239/lmt/1520585056789763/dur/457.657/mt/1557242993/fvip/4/disable_polymer/true/ip/155.94.169.201/ipbits/0/expire/1557264973/sparams/ip,ipbits,expire,id,itag,source,requiressl,ei,mm,mn,ms,mv,pl,ratebypass,mime,otfp,gir,clen,lmt,dur/signature/64B02856CE96E48AD3C426843C709C01A85769EF.357614F9E4351862AC6057DAD660C305B2F913BD/key/dg_yt0/", "filesize": null, "fps": 30, "fragments": [{"path": "range/0-218"}, {"duration": 5.339, "path": "range/1672-128140"}, {"duration": 5.338, "path": "range/128141-270666"}, {"duration": 5.339, "path": "range/270667-414788"}, {"duration": 5.339, "path": "range/414789-550932"}, {"duration": 5.338, "path": "range/550933-700198"}, {"duration": 5.339, "path": "range/700199-847341"}, {"duration": 5.339, "path": "range/847342-995254"}, {"duration": 5.338, "path": "range/995255-1142004"}, {"duration": 5.339, "path": "range/1142005-1289102"}, {"duration": 5.339, "path": "range/1289103-1438275"}, {"duration": 5.338, "path": "range/1438276-1581374"}, {"duration": 5.339, "path": "range/1581375-1728656"}, {"duration": 5.339, "path": "range/1728657-1873646"}, {"duration": 5.338, "path": "range/1873647-2018225"}, {"duration": 5.339, "path": "range/2018226-2167613"}, {"duration": 5.339, "path": "range/2167614-2317146"}, {"duration": 5.338, "path": "range/2317147-2462766"}, {"duration": 5.339, "path": "range/2462767-2611368"}, {"duration": 5.339, "path": "range/2611369-2739584"}, {"duration": 5.338, "path": "range/2739585-2878660"}, {"duration": 5.339, "path": "range/2878661-2992648"}, {"duration": 5.339, "path": "range/2992649-3141601"}, {"duration": 5.338, "path": "range/3141602-3266879"}, {"duration": 5.339, "path": "range/3266880-3394786"}, {"duration": 5.339, "path": "range/3394787-3467540"}, {"duration": 5.338, "path": "range/3467541-3616390"}, {"duration": 5.339, "path": "range/3616391-3717591"}, {"duration": 5.339, "path": "range/3717592-3800282"}, {"duration": 5.338, "path": "range/3800283-3912459"}, {"duration": 5.339, "path": "range/3912460-3996288"}, {"duration": 5.339, "path": "range/3996289-4081354"}, {"duration": 5.338, "path": "range/4081355-4196484"}, {"duration": 5.339, "path": "range/4196485-4268150"}, {"duration": 5.339, "path": "range/4268151-4363924"}, {"duration": 5.338, "path": "range/4363925-4498570"}, {"duration": 5.339, "path": "range/4498571-4572766"}, {"duration": 5.339, "path": "range/4572767-4645950"}, {"duration": 5.338, "path": "range/4645951-4722225"}, {"duration": 5.339, "path": "range/4722226-4871489"}, {"duration": 5.339, "path": "range/4871490-5020089"}, {"duration": 5.338, "path": "range/5020090-5168536"}, {"duration": 5.339, "path": "range/5168537-5314779"}, {"duration": 5.339, "path": "range/5314780-5462396"}, {"duration": 5.338, "path": "range/5462397-5606769"}, {"duration": 5.339, "path": "range/5606770-5751123"}, {"duration": 5.339, "path": "range/5751124-5899032"}, {"duration": 5.338, "path": "range/5899033-6047708"}, {"duration": 5.339, "path": "range/6047709-6195016"}, {"duration": 5.339, "path": "range/6195017-6344151"}, {"duration": 5.338, "path": "range/6344152-6494404"}, {"duration": 5.339, "path": "range/6494405-6637938"}, {"duration": 5.339, "path": "range/6637939-6784632"}, {"duration": 5.338, "path": "range/6784633-6937334"}, {"duration": 5.339, "path": "range/6937335-7086790"}, {"duration": 5.339, "path": "range/7086791-7236380"}, {"duration": 5.338, "path": "range/7236381-7385015"}, {"duration": 5.339, "path": "range/7385016-7534308"}, {"duration": 5.339, "path": "range/7534309-7683366"}, {"duration": 5.338, "path": "range/7683367-7832509"}, {"duration": 5.339, "path": "range/7832510-7981622"}, {"duration": 5.339, "path": "range/7981623-8130188"}, {"duration": 5.338, "path": "range/8130189-8279793"}, {"duration": 5.339, "path": "range/8279794-8429085"}, {"duration": 5.339, "path": "range/8429086-8578525"}, {"duration": 5.338, "path": "range/8578526-8726060"}, {"duration": 5.339, "path": "range/8726061-8874935"}, {"duration": 5.339, "path": "range/8874936-9024464"}, {"duration": 5.338, "path": "range/9024465-9173190"}, {"duration": 5.339, "path": "range/9173191-9320703"}, {"duration": 5.339, "path": "range/9320704-9469290"}, {"duration": 5.338, "path": "range/9469291-9618255"}, {"duration": 5.339, "path": "range/9618256-9765878"}, {"duration": 5.339, "path": "range/9765879-9913909"}, {"duration": 5.338, "path": "range/9913910-10060587"}, {"duration": 5.339, "path": "range/10060588-10209870"}, {"duration": 5.339, "path": "range/10209871-10357016"}, {"duration": 5.338, "path": "range/10357017-10505391"}, {"duration": 5.339, "path": "range/10505392-10653889"}, {"duration": 5.339, "path": "range/10653890-10802797"}, {"duration": 5.338, "path": "range/10802798-10951806"}, {"duration": 5.339, "path": "range/10951807-11097810"}, {"duration": 5.339, "path": "range/11097811-11247081"}, {"duration": 5.338, "path": "range/11247082-11394414"}, {"duration": 5.339, "path": "range/11394415-11542796"}, {"duration": 5.339, "path": "range/11542797-11691304"}, {"duration": 3.87, "path": "range/11691305-11797238"}], "acodec": "none"}, {"asr": null, "tbr": 242.0, "protocol": "http_dash_segments", "format": "133 - 426x240 (DASH video)", "format_note": "DASH video", "height": 240, "manifest_url": "https://manifest.googlevideo.com/api/manifest/dash/requiressl/yes/source/youtube/id/777915536295e044/itag/0/ei/7aXRXOWnD4mtkgat0ZzwCg/playback_host/r4---sn-a5ms7n7e.googlevideo.com/mm/31%2C26/mn/sn-a5ms7n7e%2Csn-9gv7lnez/ms/au%2Conr/mv/u/pl/21/hfr/all/as/fmp4_audio_clear%2Cwebm_audio_clear%2Cwebm2_audio_clear%2Cfmp4_sd_hd_clear%2Cwebm2_sd_hd_clear/mt/1557242993/fvip/4/ip/155.94.169.201/ipbits/0/expire/1557264973/sparams/ip%2Cipbits%2Cexpire%2Crequiressl%2Csource%2Cid%2Citag%2Cei%2Cplayback_host%2Cmm%2Cmn%2Cms%2Cmv%2Cpl%2Chfr%2Cas/signature/91A46A312F589A77C88E876645AE6A23EB1377B9.9030732EC6AD9C6659B25009A8423C74F9C30BB4/key/yt8", "format_id": "133", "container": "mp4_dash", "language": null, "http_headers": {"Accept-Charset": "ISO-8859-1,utf-8;q=0.7,*;q=0.7", "Accept-Language": "en-us,en;q=0.5", "Accept-Encoding": "gzip, deflate", "Accept": "text/html,application/xhtml+xml,application/xml;q=0.9,*/*;q=0.8", "User-Agent": "Mozilla/5.0 (X11; Linux x86_64; rv:59.0) Gecko/20100101 Firefox/59.0"}, "url": "https://manifest.googlevideo.com/api/manifest/dash/requiressl/yes/source/youtube/id/777915536295e044/itag/0/ei/7aXRXOWnD4mtkgat0ZzwCg/playback_host/r4---sn-a5ms7n7e.googlevideo.com/mm/31%2C26/mn/sn-a5ms7n7e%2Csn-9gv7lnez/ms/au%2Conr/mv/u/pl/21/hfr/all/as/fmp4_audio_clear%2Cwebm_audio_clear%2Cwebm2_audio_clear%2Cfmp4_sd_hd_clear%2Cwebm2_sd_hd_clear/mt/1557242993/fvip/4/ip/155.94.169.201/ipbits/0/expire/1557264973/sparams/ip%2Cipbits%2Cexpire%2Crequiressl%2Csource%2Cid%2Citag%2Cei%2Cplayback_host%2Cmm%2Cmn%2Cms%2Cmv%2Cpl%2Chfr%2Cas/signature/91A46A312F589A77C88E876645AE6A23EB1377B9.9030732EC6AD9C6659B25009A8423C74F9C30BB4/key/yt8", "vcodec": "avc1.4d400c", "width": 426, "ext": "mp4", "fragment_base_url": "https://r4---sn-a5ms7n7e.googlevideo.com/videoplayback/id/777915536295e044/itag/133/source/yt_otf/requiressl/yes/ei/7aXRXOWnD4mtkgat0ZzwCg/mm/31,26/mn/sn-a5ms7n7e,sn-9gv7lnez/ms/au,onr/mv/u/pl/21/ratebypass/yes/mime/video%2Fmp4/otfp/1/otf/1/lmt/1520524473015680/mt/1557242993/fvip/4/disable_polymer/true/ip/155.94.169.201/ipbits/0/expire/1557264973/sparams/ip,ipbits,expire,id,itag,source,requiressl,ei,mm,mn,ms,mv,pl,ratebypass,mime,otfp,otf,lmt/signature/3E9B894CBD4B4F7D8BF655FB1F07E442E25FFDD6.577D5ED3159FC4CF5A932A72F87017DBA48103DF/key/dg_yt0/", "filesize": null, "fps": 30, "fragments": [{"path": "sq/0"}, {"duration": 5.339, "path": "sq/1/dur/5.339"}, {"duration": 5.338, "path": "sq/2/dur/5.338"}, {"duration": 5.339, "path": "sq/3/dur/5.339"}, {"duration": 5.339, "path": "sq/4/dur/5.339"}, {"duration": 5.338, "path": "sq/5/dur/5.338"}, {"duration": 5.339, "path": "sq/6/dur/5.339"}, {"duration": 5.339, "path": "sq/7/dur/5.339"}, {"duration": 5.338, "path": "sq/8/dur/5.338"}, {"duration": 5.339, "path": "sq/9/dur/5.339"}, {"duration": 5.339, "path": "sq/10/dur/5.339"}, {"duration": 5.338, "path": "sq/11/dur/5.338"}, {"duration": 5.339, "path": "sq/12/dur/5.339"}, {"duration": 5.339, "path": "sq/13/dur/5.339"}, {"duration": 5.338, "path": "sq/14/dur/5.338"}, {"duration": 5.339, "path": "sq/15/dur/5.339"}, {"duration": 5.339, "path": "sq/16/dur/5.339"}, {"duration": 5.338, "path": "sq/17/dur/5.338"}, {"duration": 5.339, "path": "sq/18/dur/5.339"}, {"duration": 5.339, "path": "sq/19/dur/5.339"}, {"duration": 5.338, "path": "sq/20/dur/5.338"}, {"duration": 5.339, "path": "sq/21/dur/5.339"}, {"duration": 5.339, "path": "sq/22/dur/5.339"}, {"duration": 5.338, "path": "sq/23/dur/5.338"}, {"duration": 5.339, "path": "sq/24/dur/5.339"}, {"duration": 5.339, "path": "sq/25/dur/5.339"}, {"duration": 5.338, "path": "sq/26/dur/5.338"}, {"duration": 5.339, "path": "sq/27/dur/5.339"}, {"duration": 5.339, "path": "sq/28/dur/5.339"}, {"duration": 5.338, "path": "sq/29/dur/5.338"}, {"duration": 5.339, "path": "sq/30/dur/5.339"}, {"duration": 5.339, "path": "sq/31/dur/5.339"}, {"duration": 5.338, "path": "sq/32/dur/5.338"}, {"duration": 5.339, "path": "sq/33/dur/5.339"}, {"duration": 5.339, "path": "sq/34/dur/5.339"}, {"duration": 5.338, "path": "sq/35/dur/5.338"}, {"duration": 5.339, "path": "sq/36/dur/5.339"}, {"duration": 5.339, "path": "sq/37/dur/5.339"}, {"duration": 5.338, "path": "sq/38/dur/5.338"}, {"duration": 5.339, "path": "sq/39/dur/5.339"}, {"duration": 5.339, "path": "sq/40/dur/5.339"}, {"duration": 5.338, "path": "sq/41/dur/5.338"}, {"duration": 5.339, "path": "sq/42/dur/5.339"}, {"duration": 5.339, "path": "sq/43/dur/5.339"}, {"duration": 5.338, "path": "sq/44/dur/5.338"}, {"duration": 5.339, "path": "sq/45/dur/5.339"}, {"duration": 5.339, "path": "sq/46/dur/5.339"}, {"duration": 5.338, "path": "sq/47/dur/5.338"}, {"duration": 5.339, "path": "sq/48/dur/5.339"}, {"duration": 5.339, "path": "sq/49/dur/5.339"}, {"duration": 5.338, "path": "sq/50/dur/5.338"}, {"duration": 5.339, "path": "sq/51/dur/5.339"}, {"duration": 5.339, "path": "sq/52/dur/5.339"}, {"duration": 5.338, "path": "sq/53/dur/5.338"}, {"duration": 5.339, "path": "sq/54/dur/5.339"}, {"duration": 5.339, "path": "sq/55/dur/5.339"}, {"duration": 5.338, "path": "sq/56/dur/5.338"}, {"duration": 5.339, "path": "sq/57/dur/5.339"}, {"duration": 5.339, "path": "sq/58/dur/5.339"}, {"duration": 5.338, "path": "sq/59/dur/5.338"}, {"duration": 5.339, "path": "sq/60/dur/5.339"}, {"duration": 5.339, "path": "sq/61/dur/5.339"}, {"duration": 5.338, "path": "sq/62/dur/5.338"}, {"duration": 5.339, "path": "sq/63/dur/5.339"}, {"duration": 5.339, "path": "sq/64/dur/5.339"}, {"duration": 5.338, "path": "sq/65/dur/5.338"}, {"duration": 5.339, "path": "sq/66/dur/5.339"}, {"duration": 5.339, "path": "sq/67/dur/5.339"}, {"duration": 5.338, "path": "sq/68/dur/5.338"}, {"duration": 5.339, "path": "sq/69/dur/5.339"}, {"duration": 5.339, "path": "sq/70/dur/5.339"}, {"duration": 5.338, "path": "sq/71/dur/5.338"}, {"duration": 5.339, "path": "sq/72/dur/5.339"}, {"duration": 5.339, "path": "sq/73/dur/5.339"}, {"duration": 5.338, "path": "sq/74/dur/5.338"}, {"duration": 5.339, "path": "sq/75/dur/5.339"}, {"duration": 5.339, "path": "sq/76/dur/5.339"}, {"duration": 5.338, "path": "sq/77/dur/5.338"}, {"duration": 5.339, "path": "sq/78/dur/5.339"}, {"duration": 5.339, "path": "sq/79/dur/5.339"}, {"duration": 5.338, "path": "sq/80/dur/5.338"}, {"duration": 5.339, "path": "sq/81/dur/5.339"}, {"duration": 5.339, "path": "sq/82/dur/5.339"}, {"duration": 5.338, "path": "sq/83/dur/5.338"}, {"duration": 5.339, "path": "sq/84/dur/5.339"}, {"duration": 5.339, "path": "sq/85/dur/5.339"}, {"duration": 3.871, "path": "sq/86/dur/3.871"}], "acodec": "none"}, {"asr": null, "tbr": 420.167, "protocol": "http_dash_segments", "format": "243 - 640x360 (DASH video)", "format_note": "DASH video", "height": 360, "manifest_url": "https://manifest.googlevideo.com/api/manifest/dash/requiressl/yes/source/youtube/id/777915536295e044/itag/0/ei/7aXRXOWnD4mtkgat0ZzwCg/playback_host/r4---sn-a5ms7n7e.googlevideo.com/mm/31%2C26/mn/sn-a5ms7n7e%2Csn-9gv7lnez/ms/au%2Conr/mv/u/pl/21/hfr/all/as/fmp4_audio_clear%2Cwebm_audio_clear%2Cwebm2_audio_clear%2Cfmp4_sd_hd_clear%2Cwebm2_sd_hd_clear/mt/1557242993/fvip/4/ip/155.94.169.201/ipbits/0/expire/1557264973/sparams/ip%2Cipbits%2Cexpire%2Crequiressl%2Csource%2Cid%2Citag%2Cei%2Cplayback_host%2Cmm%2Cmn%2Cms%2Cmv%2Cpl%2Chfr%2Cas/signature/91A46A312F589A77C88E876645AE6A23EB1377B9.9030732EC6AD9C6659B25009A8423C74F9C30BB4/key/yt8", "format_id": "243", "container": "webm_dash", "language": null, "http_headers": {"Accept-Charset": "ISO-8859-1,utf-8;q=0.7,*;q=0.7", "Accept-Language": "en-us,en;q=0.5", "Accept-Encoding": "gzip, deflate", "Accept": "text/html,application/xhtml+xml,application/xml;q=0.9,*/*;q=0.8", "User-Agent": "Mozilla/5.0 (X11; Linux x86_64; rv:59.0) Gecko/20100101 Firefox/59.0"}, "url": "https://manifest.googlevideo.com/api/manifest/dash/requiressl/yes/source/youtube/id/777915536295e044/itag/0/ei/7aXRXOWnD4mtkgat0ZzwCg/playback_host/r4---sn-a5ms7n7e.googlevideo.com/mm/31%2C26/mn/sn-a5ms7n7e%2Csn-9gv7lnez/ms/au%2Conr/mv/u/pl/21/hfr/all/as/fmp4_audio_clear%2Cwebm_audio_clear%2Cwebm2_audio_clear%2Cfmp4_sd_hd_clear%2Cwebm2_sd_hd_clear/mt/1557242993/fvip/4/ip/155.94.169.201/ipbits/0/expire/1557264973/sparams/ip%2Cipbits%2Cexpire%2Crequiressl%2Csource%2Cid%2Citag%2Cei%2Cplayback_host%2Cmm%2Cmn%2Cms%2Cmv%2Cpl%2Chfr%2Cas/signature/91A46A312F589A77C88E876645AE6A23EB1377B9.9030732EC6AD9C6659B25009A8423C74F9C30BB4/key/yt8", "vcodec": "vp9", "width": 640, "ext": "webm", "fragment_base_url": "https://r4---sn-a5ms7n7e.googlevideo.com/videoplayback/id/777915536295e044/itag/243/source/youtube/requiressl/yes/ei/7aXRXOWnD4mtkgat0ZzwCg/mm/31,26/mn/sn-a5ms7n7e,sn-9gv7lnez/ms/au,onr/mv/u/pl/21/ratebypass/yes/mime/video%2Fwebm/otfp/1/gir/yes/clen/21954508/lmt/1520585119756358/dur/457.657/mt/1557242993/fvip/4/disable_polymer/true/ip/155.94.169.201/ipbits/0/expire/1557264973/sparams/ip,ipbits,expire,id,itag,source,requiressl,ei,mm,mn,ms,mv,pl,ratebypass,mime,otfp,gir,clen,lmt,dur/signature/56F0B57807E6AC0F4457B2336CC73469683A29FD.BC7A511953DBA6F7DC5C476B844985556A98E8/key/dg_yt0/", "filesize": null, "fps": 30, "fragments": [{"path": "range/0-219"}, {"duration": 5.339, "path": "range/1692-228690"}, {"duration": 5.338, "path": "range/228691-490357"}, {"duration": 5.339, "path": "range/490358-753929"}, {"duration": 5.339, "path": "range/753930-1022760"}, {"duration": 5.338, "path": "range/1022761-1296186"}, {"duration": 5.339, "path": "range/1296187-1574350"}, {"duration": 5.339, "path": "range/1574351-1845953"}, {"duration": 5.338, "path": "range/1845954-2115750"}, {"duration": 5.339, "path": "range/2115751-2385790"}, {"duration": 5.339, "path": "range/2385791-2656390"}, {"duration": 5.338, "path": "range/2656391-2926431"}, {"duration": 5.339, "path": "range/2926432-3203254"}, {"duration": 5.339, "path": "range/3203255-3465516"}, {"duration": 5.338, "path": "range/3465517-3731652"}, {"duration": 5.339, "path": "range/3731653-4004974"}, {"duration": 5.339, "path": "range/4004975-4279449"}, {"duration": 5.338, "path": "range/4279450-4554320"}, {"duration": 5.339, "path": "range/4554321-4823326"}, {"duration": 5.339, "path": "range/4823327-5078696"}, {"duration": 5.338, "path": "range/5078697-5345763"}, {"duration": 5.339, "path": "range/5345764-5574024"}, {"duration": 5.339, "path": "range/5574025-5845799"}, {"duration": 5.338, "path": "range/5845800-6092449"}, {"duration": 5.339, "path": "range/6092450-6337866"}, {"duration": 5.339, "path": "range/6337867-6487190"}, {"duration": 5.338, "path": "range/6487191-6760208"}, {"duration": 5.339, "path": "range/6760209-6965899"}, {"duration": 5.339, "path": "range/6965900-7135420"}, {"duration": 5.338, "path": "range/7135421-7357988"}, {"duration": 5.339, "path": "range/7357989-7531343"}, {"duration": 5.339, "path": "range/7531344-7706037"}, {"duration": 5.338, "path": "range/7706038-7930113"}, {"duration": 5.339, "path": "range/7930114-8075816"}, {"duration": 5.339, "path": "range/8075817-8262518"}, {"duration": 5.338, "path": "range/8262519-8520303"}, {"duration": 5.339, "path": "range/8520304-8677290"}, {"duration": 5.339, "path": "range/8677291-8830715"}, {"duration": 5.338, "path": "range/8830716-8997213"}, {"duration": 5.339, "path": "range/8997214-9269951"}, {"duration": 5.339, "path": "range/9269952-9541911"}, {"duration": 5.338, "path": "range/9541912-9813961"}, {"duration": 5.339, "path": "range/9813962-10085217"}, {"duration": 5.339, "path": "range/10085218-10355509"}, {"duration": 5.338, "path": "range/10355510-10623734"}, {"duration": 5.339, "path": "range/10623735-10895548"}, {"duration": 5.339, "path": "range/10895549-11166118"}, {"duration": 5.338, "path": "range/11166119-11438370"}, {"duration": 5.339, "path": "range/11438371-11702963"}, {"duration": 5.339, "path": "range/11702964-11976166"}, {"duration": 5.338, "path": "range/11976167-12250650"}, {"duration": 5.339, "path": "range/12250651-12514918"}, {"duration": 5.339, "path": "range/12514919-12788387"}, {"duration": 5.338, "path": "range/12788388-13068744"}, {"duration": 5.339, "path": "range/13068745-13338372"}, {"duration": 5.339, "path": "range/13338373-13611753"}, {"duration": 5.338, "path": "range/13611754-13883766"}, {"duration": 5.339, "path": "range/13883767-14156192"}, {"duration": 5.339, "path": "range/14156193-14424237"}, {"duration": 5.338, "path": "range/14424238-14694489"}, {"duration": 5.339, "path": "range/14694490-14970824"}, {"duration": 5.339, "path": "range/14970825-15243018"}, {"duration": 5.338, "path": "range/15243019-15516965"}, {"duration": 5.339, "path": "range/15516966-15790392"}, {"duration": 5.339, "path": "range/15790393-16062600"}, {"duration": 5.338, "path": "range/16062601-16334487"}, {"duration": 5.339, "path": "range/16334488-16607205"}, {"duration": 5.339, "path": "range/16607206-16880541"}, {"duration": 5.338, "path": "range/16880542-17153229"}, {"duration": 5.339, "path": "range/17153230-17422382"}, {"duration": 5.339, "path": "range/17422383-17694858"}, {"duration": 5.338, "path": "range/17694859-17967470"}, {"duration": 5.339, "path": "range/17967471-18236950"}, {"duration": 5.339, "path": "range/18236951-18503974"}, {"duration": 5.338, "path": "range/18503975-18772957"}, {"duration": 5.339, "path": "range/18772958-19043177"}, {"duration": 5.339, "path": "range/19043178-19316737"}, {"duration": 5.338, "path": "range/19316738-19586148"}, {"duration": 5.339, "path": "range/19586149-19858720"}, {"duration": 5.339, "path": "range/19858721-20132509"}, {"duration": 5.338, "path": "range/20132510-20405620"}, {"duration": 5.339, "path": "range/20405621-20677685"}, {"duration": 5.339, "path": "range/20677686-20950597"}, {"duration": 5.338, "path": "range/20950598-21219506"}, {"duration": 5.339, "path": "range/21219507-21487401"}, {"duration": 5.339, "path": "range/21487402-21761089"}, {"duration": 3.87, "path": "range/21761090-21954507"}], "acodec": "none"}, {"asr": null, "tbr": 639.634, "protocol": "http_dash_segments", "format": "134 - 640x360 (DASH video)", "format_note": "DASH video", "height": 360, "manifest_url": "https://manifest.googlevideo.com/api/manifest/dash/requiressl/yes/source/youtube/id/777915536295e044/itag/0/ei/7aXRXOWnD4mtkgat0ZzwCg/playback_host/r4---sn-a5ms7n7e.googlevideo.com/mm/31%2C26/mn/sn-a5ms7n7e%2Csn-9gv7lnez/ms/au%2Conr/mv/u/pl/21/hfr/all/as/fmp4_audio_clear%2Cwebm_audio_clear%2Cwebm2_audio_clear%2Cfmp4_sd_hd_clear%2Cwebm2_sd_hd_clear/mt/1557242993/fvip/4/ip/155.94.169.201/ipbits/0/expire/1557264973/sparams/ip%2Cipbits%2Cexpire%2Crequiressl%2Csource%2Cid%2Citag%2Cei%2Cplayback_host%2Cmm%2Cmn%2Cms%2Cmv%2Cpl%2Chfr%2Cas/signature/91A46A312F589A77C88E876645AE6A23EB1377B9.9030732EC6AD9C6659B25009A8423C74F9C30BB4/key/yt8", "format_id": "134", "container": "mp4_dash", "language": null, "http_headers": {"Accept-Charset": "ISO-8859-1,utf-8;q=0.7,*;q=0.7", "Accept-Language": "en-us,en;q=0.5", "Accept-Encoding": "gzip, deflate", "Accept": "text/html,application/xhtml+xml,application/xml;q=0.9,*/*;q=0.8", "User-Agent": "Mozilla/5.0 (X11; Linux x86_64; rv:59.0) Gecko/20100101 Firefox/59.0"}, "url": "https://manifest.googlevideo.com/api/manifest/dash/requiressl/yes/source/youtube/id/777915536295e044/itag/0/ei/7aXRXOWnD4mtkgat0ZzwCg/playback_host/r4---sn-a5ms7n7e.googlevideo.com/mm/31%2C26/mn/sn-a5ms7n7e%2Csn-9gv7lnez/ms/au%2Conr/mv/u/pl/21/hfr/all/as/fmp4_audio_clear%2Cwebm_audio_clear%2Cwebm2_audio_clear%2Cfmp4_sd_hd_clear%2Cwebm2_sd_hd_clear/mt/1557242993/fvip/4/ip/155.94.169.201/ipbits/0/expire/1557264973/sparams/ip%2Cipbits%2Cexpire%2Crequiressl%2Csource%2Cid%2Citag%2Cei%2Cplayback_host%2Cmm%2Cmn%2Cms%2Cmv%2Cpl%2Chfr%2Cas/signature/91A46A312F589A77C88E876645AE6A23EB1377B9.9030732EC6AD9C6659B25009A8423C74F9C30BB4/key/yt8", "vcodec": "avc1.4d401e", "width": 640, "ext": "mp4", "fragment_base_url": "https://r4---sn-a5ms7n7e.googlevideo.com/videoplayback/id/777915536295e044/itag/134/source/youtube/requiressl/yes/ei/7aXRXOWnD4mtkgat0ZzwCg/mm/31,26/mn/sn-a5ms7n7e,sn-9gv7lnez/ms/au,onr/mv/u/pl/21/ratebypass/yes/mime/video%2Fmp4/otfp/1/gir/yes/clen/30330047/lmt/1520524388378509/dur/457.657/mt/1557242993/fvip/4/disable_polymer/true/ip/155.94.169.201/ipbits/0/expire/1557264973/sparams/ip,ipbits,expire,id,itag,source,requiressl,ei,mm,mn,ms,mv,pl,ratebypass,mime,otfp,gir,clen,lmt,dur/signature/137F65284C94CB9F3AE821B7A4D8EA3376000857.80E822A62C18D20E82DE6C98530C40837FF23274/key/dg_yt0/", "filesize": null, "fps": 30, "fragments": [{"path": "range/0-712"}, {"duration": 5.339, "path": "range/1777-424583"}, {"duration": 5.338, "path": "range/424584-848715"}, {"duration": 5.339, "path": "range/848716-1271046"}, {"duration": 5.339, "path": "range/1271047-1694630"}, {"duration": 5.338, "path": "range/1694631-2118407"}, {"duration": 5.339, "path": "range/2118408-2491497"}, {"duration": 5.339, "path": "range/2491498-2915580"}, {"duration": 5.338, "path": "range/2915581-3338889"}, {"duration": 5.339, "path": "range/3338890-3753674"}, {"duration": 5.339, "path": "range/3753675-4062721"}, {"duration": 5.338, "path": "range/4062722-4390324"}, {"duration": 5.339, "path": "range/4390325-4783207"}, {"duration": 5.339, "path": "range/4783208-5205501"}, {"duration": 5.338, "path": "range/5205502-5548160"}, {"duration": 5.339, "path": "range/5548161-5823392"}, {"duration": 5.339, "path": "range/5823393-6133111"}, {"duration": 5.338, "path": "range/6133112-6493356"}, {"duration": 5.339, "path": "range/6493357-6916677"}, {"duration": 5.339, "path": "range/6916678-7200730"}, {"duration": 5.338, "path": "range/7200731-7480280"}, {"duration": 5.339, "path": "range/7480281-7720547"}, {"duration": 5.339, "path": "range/7720548-8040520"}, {"duration": 5.338, "path": "range/8040521-8333005"}, {"duration": 5.339, "path": "range/8333006-8581361"}, {"duration": 5.339, "path": "range/8581362-8773020"}, {"duration": 5.338, "path": "range/8773021-9062466"}, {"duration": 5.339, "path": "range/9062467-9301169"}, {"duration": 5.339, "path": "range/9301170-9490489"}, {"duration": 5.338, "path": "range/9490490-9705390"}, {"duration": 5.339, "path": "range/9705391-9898448"}, {"duration": 5.339, "path": "range/9898449-10085611"}, {"duration": 5.338, "path": "range/10085612-10302457"}, {"duration": 5.339, "path": "range/10302458-10498266"}, {"duration": 5.339, "path": "range/10498267-10719050"}, {"duration": 5.338, "path": "range/10719051-11036491"}, {"duration": 5.339, "path": "range/11036492-11237574"}, {"duration": 5.339, "path": "range/11237575-11430307"}, {"duration": 5.338, "path": "range/11430308-11624560"}, {"duration": 5.339, "path": "range/11624561-12050973"}, {"duration": 5.339, "path": "range/12050974-12474419"}, {"duration": 5.338, "path": "range/12474420-12876654"}, {"duration": 5.339, "path": "range/12876655-13182284"}, {"duration": 5.339, "path": "range/13182285-13559164"}, {"duration": 5.338, "path": "range/13559165-13984616"}, {"duration": 5.339, "path": "range/13984617-14408100"}, {"duration": 5.339, "path": "range/14408101-14831784"}, {"duration": 5.338, "path": "range/14831785-15255245"}, {"duration": 5.339, "path": "range/15255246-15632398"}, {"duration": 5.339, "path": "range/15632399-15901133"}, {"duration": 5.338, "path": "range/15901134-16187224"}, {"duration": 5.339, "path": "range/16187225-16485610"}, {"duration": 5.339, "path": "range/16485611-16738166"}, {"duration": 5.338, "path": "range/16738167-17068722"}, {"duration": 5.339, "path": "range/17068723-17427030"}, {"duration": 5.339, "path": "range/17427031-17822595"}, {"duration": 5.338, "path": "range/17822596-18246834"}, {"duration": 5.339, "path": "range/18246835-18628987"}, {"duration": 5.339, "path": "range/18628988-18980350"}, {"duration": 5.338, "path": "range/18980351-19337576"}, {"duration": 5.339, "path": "range/19337577-19646574"}, {"duration": 5.339, "path": "range/19646575-20073450"}, {"duration": 5.338, "path": "range/20073451-20498166"}, {"duration": 5.339, "path": "range/20498167-20921907"}, {"duration": 5.339, "path": "range/20921908-21345647"}, {"duration": 5.338, "path": "range/21345648-21770115"}, {"duration": 5.339, "path": "range/21770116-22193955"}, {"duration": 5.339, "path": "range/22193956-22618599"}, {"duration": 5.338, "path": "range/22618600-23042866"}, {"duration": 5.339, "path": "range/23042867-23466247"}, {"duration": 5.339, "path": "range/23466248-23889927"}, {"duration": 5.338, "path": "range/23889928-24313535"}, {"duration": 5.339, "path": "range/24313536-24738438"}, {"duration": 5.339, "path": "range/24738439-25162165"}, {"duration": 5.338, "path": "range/25162166-25586672"}, {"duration": 5.339, "path": "range/25586673-25934580"}, {"duration": 5.339, "path": "range/25934581-26328870"}, {"duration": 5.338, "path": "range/26328871-26752093"}, {"duration": 5.339, "path": "range/26752094-27175963"}, {"duration": 5.339, "path": "range/27175964-27601741"}, {"duration": 5.338, "path": "range/27601742-28025887"}, {"duration": 5.339, "path": "range/28025888-28448876"}, {"duration": 5.339, "path": "range/28448877-28800208"}, {"duration": 5.338, "path": "range/28800209-29174695"}, {"duration": 5.339, "path": "range/29174696-29598277"}, {"duration": 5.339, "path": "range/29598278-30022802"}, {"duration": 3.871, "path": "range/30022803-30330046"}], "acodec": "none"}, {"asr": null, "tbr": 768.26, "protocol": "http_dash_segments", "format": "244 - 854x480 (DASH video)", "format_note": "DASH video", "height": 480, "manifest_url": "https://manifest.googlevideo.com/api/manifest/dash/requiressl/yes/source/youtube/id/777915536295e044/itag/0/ei/7aXRXOWnD4mtkgat0ZzwCg/playback_host/r4---sn-a5ms7n7e.googlevideo.com/mm/31%2C26/mn/sn-a5ms7n7e%2Csn-9gv7lnez/ms/au%2Conr/mv/u/pl/21/hfr/all/as/fmp4_audio_clear%2Cwebm_audio_clear%2Cwebm2_audio_clear%2Cfmp4_sd_hd_clear%2Cwebm2_sd_hd_clear/mt/1557242993/fvip/4/ip/155.94.169.201/ipbits/0/expire/1557264973/sparams/ip%2Cipbits%2Cexpire%2Crequiressl%2Csource%2Cid%2Citag%2Cei%2Cplayback_host%2Cmm%2Cmn%2Cms%2Cmv%2Cpl%2Chfr%2Cas/signature/91A46A312F589A77C88E876645AE6A23EB1377B9.9030732EC6AD9C6659B25009A8423C74F9C30BB4/key/yt8", "format_id": "244", "container": "webm_dash", "language": null, "http_headers": {"Accept-Charset": "ISO-8859-1,utf-8;q=0.7,*;q=0.7", "Accept-Language": "en-us,en;q=0.5", "Accept-Encoding": "gzip, deflate", "Accept": "text/html,application/xhtml+xml,application/xml;q=0.9,*/*;q=0.8", "User-Agent": "Mozilla/5.0 (X11; Linux x86_64; rv:59.0) Gecko/20100101 Firefox/59.0"}, "url": "https://manifest.googlevideo.com/api/manifest/dash/requiressl/yes/source/youtube/id/777915536295e044/itag/0/ei/7aXRXOWnD4mtkgat0ZzwCg/playback_host/r4---sn-a5ms7n7e.googlevideo.com/mm/31%2C26/mn/sn-a5ms7n7e%2Csn-9gv7lnez/ms/au%2Conr/mv/u/pl/21/hfr/all/as/fmp4_audio_clear%2Cwebm_audio_clear%2Cwebm2_audio_clear%2Cfmp4_sd_hd_clear%2Cwebm2_sd_hd_clear/mt/1557242993/fvip/4/ip/155.94.169.201/ipbits/0/expire/1557264973/sparams/ip%2Cipbits%2Cexpire%2Crequiressl%2Csource%2Cid%2Citag%2Cei%2Cplayback_host%2Cmm%2Cmn%2Cms%2Cmv%2Cpl%2Chfr%2Cas/signature/91A46A312F589A77C88E876645AE6A23EB1377B9.9030732EC6AD9C6659B25009A8423C74F9C30BB4/key/yt8", "vcodec": "vp9", "width": 854, "ext": "webm", "fragment_base_url": "https://r4---sn-a5ms7n7e.googlevideo.com/videoplayback/id/777915536295e044/itag/244/source/youtube/requiressl/yes/ei/7aXRXOWnD4mtkgat0ZzwCg/mm/31,26/mn/sn-a5ms7n7e,sn-9gv7lnez/ms/au,onr/mv/u/pl/21/ratebypass/yes/mime/video%2Fwebm/otfp/1/gir/yes/clen/39785370/lmt/1520585080220864/dur/457.657/mt/1557242993/fvip/4/disable_polymer/true/ip/155.94.169.201/ipbits/0/expire/1557264973/sparams/ip,ipbits,expire,id,itag,source,requiressl,ei,mm,mn,ms,mv,pl,ratebypass,mime,otfp,gir,clen,lmt,dur/signature/145A322F12E9B1115F235D29D505518CEC6F46A8.93BDD47F55E5FF6D3D09E02EF64B60F02A8258B7/key/dg_yt0/", "filesize": null, "fps": 30, "fragments": [{"path": "range/0-219"}, {"duration": 5.339, "path": "range/1719-422692"}, {"duration": 5.338, "path": "range/422693-854382"}, {"duration": 5.339, "path": "range/854383-1346548"}, {"duration": 5.339, "path": "range/1346549-1788880"}, {"duration": 5.338, "path": "range/1788881-2292379"}, {"duration": 5.339, "path": "range/2292380-2797282"}, {"duration": 5.339, "path": "range/2797283-3299957"}, {"duration": 5.338, "path": "range/3299958-3803853"}, {"duration": 5.339, "path": "range/3803854-4307487"}, {"duration": 5.339, "path": "range/4307488-4800858"}, {"duration": 5.338, "path": "range/4800859-5303161"}, {"duration": 5.339, "path": "range/5303162-5805341"}, {"duration": 5.339, "path": "range/5805342-6286983"}, {"duration": 5.338, "path": "range/6286984-6785324"}, {"duration": 5.339, "path": "range/6785325-7242407"}, {"duration": 5.339, "path": "range/7242408-7745868"}, {"duration": 5.338, "path": "range/7745869-8247996"}, {"duration": 5.339, "path": "range/8247997-8752303"}, {"duration": 5.339, "path": "range/8752304-9192482"}, {"duration": 5.338, "path": "range/9192483-9643897"}, {"duration": 5.339, "path": "range/9643898-10027530"}, {"duration": 5.339, "path": "range/10027531-10530453"}, {"duration": 5.338, "path": "range/10530454-10954949"}, {"duration": 5.339, "path": "range/10954950-11355959"}, {"duration": 5.339, "path": "range/11355960-11603229"}, {"duration": 5.338, "path": "range/11603230-12063390"}, {"duration": 5.339, "path": "range/12063391-12413305"}, {"duration": 5.339, "path": "range/12413306-12701332"}, {"duration": 5.338, "path": "range/12701333-13067006"}, {"duration": 5.339, "path": "range/13067007-13362822"}, {"duration": 5.339, "path": "range/13362823-13663679"}, {"duration": 5.338, "path": "range/13663680-14036105"}, {"duration": 5.339, "path": "range/14036106-14288618"}, {"duration": 5.339, "path": "range/14288619-14592982"}, {"duration": 5.338, "path": "range/14592983-15033121"}, {"duration": 5.339, "path": "range/15033122-15310860"}, {"duration": 5.339, "path": "range/15310861-15585855"}, {"duration": 5.338, "path": "range/15585856-15869301"}, {"duration": 5.339, "path": "range/15869302-16373718"}, {"duration": 5.339, "path": "range/16373719-16884824"}, {"duration": 5.338, "path": "range/16884825-17389233"}, {"duration": 5.339, "path": "range/17389234-17889212"}, {"duration": 5.339, "path": "range/17889213-18394267"}, {"duration": 5.338, "path": "range/18394268-18896539"}, {"duration": 5.339, "path": "range/18896540-19399473"}, {"duration": 5.339, "path": "range/19399474-19905592"}, {"duration": 5.338, "path": "range/19905593-20406939"}, {"duration": 5.339, "path": "range/20406940-20905533"}, {"duration": 5.339, "path": "range/20905534-21379005"}, {"duration": 5.338, "path": "range/21379006-21884365"}, {"duration": 5.339, "path": "range/21884366-22379059"}, {"duration": 5.339, "path": "range/22379060-22847667"}, {"duration": 5.338, "path": "range/22847668-23353962"}, {"duration": 5.339, "path": "range/23353963-23862864"}, {"duration": 5.339, "path": "range/23862865-24362441"}, {"duration": 5.338, "path": "range/24362442-24861341"}, {"duration": 5.339, "path": "range/24861342-25359812"}, {"duration": 5.339, "path": "range/25359813-25865759"}, {"duration": 5.338, "path": "range/25865760-26353668"}, {"duration": 5.339, "path": "range/26353669-26858845"}, {"duration": 5.339, "path": "range/26858846-27358342"}, {"duration": 5.338, "path": "range/27358343-27863884"}, {"duration": 5.339, "path": "range/27863885-28370473"}, {"duration": 5.339, "path": "range/28370474-28866529"}, {"duration": 5.338, "path": "range/28866530-29372607"}, {"duration": 5.339, "path": "range/29372608-29871763"}, {"duration": 5.339, "path": "range/29871764-30368490"}, {"duration": 5.338, "path": "range/30368491-30868338"}, {"duration": 5.339, "path": "range/30868339-31381056"}, {"duration": 5.339, "path": "range/31381057-31879655"}, {"duration": 5.338, "path": "range/31879656-32383260"}, {"duration": 5.339, "path": "range/32383261-32878301"}, {"duration": 5.339, "path": "range/32878302-33368019"}, {"duration": 5.338, "path": "range/33368020-33874903"}, {"duration": 5.339, "path": "range/33874904-34378679"}, {"duration": 5.339, "path": "range/34378680-34885150"}, {"duration": 5.338, "path": "range/34885151-35387671"}, {"duration": 5.339, "path": "range/35387672-35889256"}, {"duration": 5.339, "path": "range/35889257-36394503"}, {"duration": 5.338, "path": "range/36394504-36898553"}, {"duration": 5.339, "path": "range/36898554-37400972"}, {"duration": 5.339, "path": "range/37400973-37903396"}, {"duration": 5.338, "path": "range/37903397-38406968"}, {"duration": 5.339, "path": "range/38406969-38909709"}, {"duration": 5.339, "path": "range/38909710-39417820"}, {"duration": 3.87, "path": "range/39417821-39785369"}], "acodec": "none"}, {"asr": null, "tbr": 1155.0, "protocol": "http_dash_segments", "format": "135 - 854x480 (DASH video)", "format_note": "DASH video", "height": 480, "manifest_url": "https://manifest.googlevideo.com/api/manifest/dash/requiressl/yes/source/youtube/id/777915536295e044/itag/0/ei/7aXRXOWnD4mtkgat0ZzwCg/playback_host/r4---sn-a5ms7n7e.googlevideo.com/mm/31%2C26/mn/sn-a5ms7n7e%2Csn-9gv7lnez/ms/au%2Conr/mv/u/pl/21/hfr/all/as/fmp4_audio_clear%2Cwebm_audio_clear%2Cwebm2_audio_clear%2Cfmp4_sd_hd_clear%2Cwebm2_sd_hd_clear/mt/1557242993/fvip/4/ip/155.94.169.201/ipbits/0/expire/1557264973/sparams/ip%2Cipbits%2Cexpire%2Crequiressl%2Csource%2Cid%2Citag%2Cei%2Cplayback_host%2Cmm%2Cmn%2Cms%2Cmv%2Cpl%2Chfr%2Cas/signature/91A46A312F589A77C88E876645AE6A23EB1377B9.9030732EC6AD9C6659B25009A8423C74F9C30BB4/key/yt8", "format_id": "135", "container": "mp4_dash", "language": null, "http_headers": {"Accept-Charset": "ISO-8859-1,utf-8;q=0.7,*;q=0.7", "Accept-Language": "en-us,en;q=0.5", "Accept-Encoding": "gzip, deflate", "Accept": "text/html,application/xhtml+xml,application/xml;q=0.9,*/*;q=0.8", "User-Agent": "Mozilla/5.0 (X11; Linux x86_64; rv:59.0) Gecko/20100101 Firefox/59.0"}, "url": "https://manifest.googlevideo.com/api/manifest/dash/requiressl/yes/source/youtube/id/777915536295e044/itag/0/ei/7aXRXOWnD4mtkgat0ZzwCg/playback_host/r4---sn-a5ms7n7e.googlevideo.com/mm/31%2C26/mn/sn-a5ms7n7e%2Csn-9gv7lnez/ms/au%2Conr/mv/u/pl/21/hfr/all/as/fmp4_audio_clear%2Cwebm_audio_clear%2Cwebm2_audio_clear%2Cfmp4_sd_hd_clear%2Cwebm2_sd_hd_clear/mt/1557242993/fvip/4/ip/155.94.169.201/ipbits/0/expire/1557264973/sparams/ip%2Cipbits%2Cexpire%2Crequiressl%2Csource%2Cid%2Citag%2Cei%2Cplayback_host%2Cmm%2Cmn%2Cms%2Cmv%2Cpl%2Chfr%2Cas/signature/91A46A312F589A77C88E876645AE6A23EB1377B9.9030732EC6AD9C6659B25009A8423C74F9C30BB4/key/yt8", "vcodec": "avc1.4d4014", "width": 854, "ext": "mp4", "fragment_base_url": "https://r4---sn-a5ms7n7e.googlevideo.com/videoplayback/id/777915536295e044/itag/135/source/yt_otf/requiressl/yes/ei/7aXRXOWnD4mtkgat0ZzwCg/mm/31,26/mn/sn-a5ms7n7e,sn-9gv7lnez/ms/au,onr/mv/u/pl/21/ratebypass/yes/mime/video%2Fmp4/otfp/1/otf/1/lmt/1520524473015680/mt/1557242993/fvip/4/disable_polymer/true/ip/155.94.169.201/ipbits/0/expire/1557264973/sparams/ip,ipbits,expire,id,itag,source,requiressl,ei,mm,mn,ms,mv,pl,ratebypass,mime,otfp,otf,lmt/signature/0D9CD137A21EDAA1C1C1F0A7D83C4D8EC1B86F76.47BF3B313AB1773EAAD3C28662C42BFEE3F69946/key/dg_yt0/", "filesize": null, "fps": 30, "fragments": [{"path": "sq/0"}, {"duration": 5.339, "path": "sq/1/dur/5.339"}, {"duration": 5.338, "path": "sq/2/dur/5.338"}, {"duration": 5.339, "path": "sq/3/dur/5.339"}, {"duration": 5.339, "path": "sq/4/dur/5.339"}, {"duration": 5.338, "path": "sq/5/dur/5.338"}, {"duration": 5.339, "path": "sq/6/dur/5.339"}, {"duration": 5.339, "path": "sq/7/dur/5.339"}, {"duration": 5.338, "path": "sq/8/dur/5.338"}, {"duration": 5.339, "path": "sq/9/dur/5.339"}, {"duration": 5.339, "path": "sq/10/dur/5.339"}, {"duration": 5.338, "path": "sq/11/dur/5.338"}, {"duration": 5.339, "path": "sq/12/dur/5.339"}, {"duration": 5.339, "path": "sq/13/dur/5.339"}, {"duration": 5.338, "path": "sq/14/dur/5.338"}, {"duration": 5.339, "path": "sq/15/dur/5.339"}, {"duration": 5.339, "path": "sq/16/dur/5.339"}, {"duration": 5.338, "path": "sq/17/dur/5.338"}, {"duration": 5.339, "path": "sq/18/dur/5.339"}, {"duration": 5.339, "path": "sq/19/dur/5.339"}, {"duration": 5.338, "path": "sq/20/dur/5.338"}, {"duration": 5.339, "path": "sq/21/dur/5.339"}, {"duration": 5.339, "path": "sq/22/dur/5.339"}, {"duration": 5.338, "path": "sq/23/dur/5.338"}, {"duration": 5.339, "path": "sq/24/dur/5.339"}, {"duration": 5.339, "path": "sq/25/dur/5.339"}, {"duration": 5.338, "path": "sq/26/dur/5.338"}, {"duration": 5.339, "path": "sq/27/dur/5.339"}, {"duration": 5.339, "path": "sq/28/dur/5.339"}, {"duration": 5.338, "path": "sq/29/dur/5.338"}, {"duration": 5.339, "path": "sq/30/dur/5.339"}, {"duration": 5.339, "path": "sq/31/dur/5.339"}, {"duration": 5.338, "path": "sq/32/dur/5.338"}, {"duration": 5.339, "path": "sq/33/dur/5.339"}, {"duration": 5.339, "path": "sq/34/dur/5.339"}, {"duration": 5.338, "path": "sq/35/dur/5.338"}, {"duration": 5.339, "path": "sq/36/dur/5.339"}, {"duration": 5.339, "path": "sq/37/dur/5.339"}, {"duration": 5.338, "path": "sq/38/dur/5.338"}, {"duration": 5.339, "path": "sq/39/dur/5.339"}, {"duration": 5.339, "path": "sq/40/dur/5.339"}, {"duration": 5.338, "path": "sq/41/dur/5.338"}, {"duration": 5.339, "path": "sq/42/dur/5.339"}, {"duration": 5.339, "path": "sq/43/dur/5.339"}, {"duration": 5.338, "path": "sq/44/dur/5.338"}, {"duration": 5.339, "path": "sq/45/dur/5.339"}, {"duration": 5.339, "path": "sq/46/dur/5.339"}, {"duration": 5.338, "path": "sq/47/dur/5.338"}, {"duration": 5.339, "path": "sq/48/dur/5.339"}, {"duration": 5.339, "path": "sq/49/dur/5.339"}, {"duration": 5.338, "path": "sq/50/dur/5.338"}, {"duration": 5.339, "path": "sq/51/dur/5.339"}, {"duration": 5.339, "path": "sq/52/dur/5.339"}, {"duration": 5.338, "path": "sq/53/dur/5.338"}, {"duration": 5.339, "path": "sq/54/dur/5.339"}, {"duration": 5.339, "path": "sq/55/dur/5.339"}, {"duration": 5.338, "path": "sq/56/dur/5.338"}, {"duration": 5.339, "path": "sq/57/dur/5.339"}, {"duration": 5.339, "path": "sq/58/dur/5.339"}, {"duration": 5.338, "path": "sq/59/dur/5.338"}, {"duration": 5.339, "path": "sq/60/dur/5.339"}, {"duration": 5.339, "path": "sq/61/dur/5.339"}, {"duration": 5.338, "path": "sq/62/dur/5.338"}, {"duration": 5.339, "path": "sq/63/dur/5.339"}, {"duration": 5.339, "path": "sq/64/dur/5.339"}, {"duration": 5.338, "path": "sq/65/dur/5.338"}, {"duration": 5.339, "path": "sq/66/dur/5.339"}, {"duration": 5.339, "path": "sq/67/dur/5.339"}, {"duration": 5.338, "path": "sq/68/dur/5.338"}, {"duration": 5.339, "path": "sq/69/dur/5.339"}, {"duration": 5.339, "path": "sq/70/dur/5.339"}, {"duration": 5.338, "path": "sq/71/dur/5.338"}, {"duration": 5.339, "path": "sq/72/dur/5.339"}, {"duration": 5.339, "path": "sq/73/dur/5.339"}, {"duration": 5.338, "path": "sq/74/dur/5.338"}, {"duration": 5.339, "path": "sq/75/dur/5.339"}, {"duration": 5.339, "path": "sq/76/dur/5.339"}, {"duration": 5.338, "path": "sq/77/dur/5.338"}, {"duration": 5.339, "path": "sq/78/dur/5.339"}, {"duration": 5.339, "path": "sq/79/dur/5.339"}, {"duration": 5.338, "path": "sq/80/dur/5.338"}, {"duration": 5.339, "path": "sq/81/dur/5.339"}, {"duration": 5.339, "path": "sq/82/dur/5.339"}, {"duration": 5.338, "path": "sq/83/dur/5.338"}, {"duration": 5.339, "path": "sq/84/dur/5.339"}, {"duration": 5.339, "path": "sq/85/dur/5.339"}, {"duration": 3.871, "path": "sq/86/dur/3.871"}], "acodec": "none"}, {"asr": null, "tbr": 1551.862, "protocol": "http_dash_segments", "format": "247 - 1280x720 (DASH video)", "format_note": "DASH video", "height": 720, "manifest_url": "https://manifest.googlevideo.com/api/manifest/dash/requiressl/yes/source/youtube/id/777915536295e044/itag/0/ei/7aXRXOWnD4mtkgat0ZzwCg/playback_host/r4---sn-a5ms7n7e.googlevideo.com/mm/31%2C26/mn/sn-a5ms7n7e%2Csn-9gv7lnez/ms/au%2Conr/mv/u/pl/21/hfr/all/as/fmp4_audio_clear%2Cwebm_audio_clear%2Cwebm2_audio_clear%2Cfmp4_sd_hd_clear%2Cwebm2_sd_hd_clear/mt/1557242993/fvip/4/ip/155.94.169.201/ipbits/0/expire/1557264973/sparams/ip%2Cipbits%2Cexpire%2Crequiressl%2Csource%2Cid%2Citag%2Cei%2Cplayback_host%2Cmm%2Cmn%2Cms%2Cmv%2Cpl%2Chfr%2Cas/signature/91A46A312F589A77C88E876645AE6A23EB1377B9.9030732EC6AD9C6659B25009A8423C74F9C30BB4/key/yt8", "format_id": "247", "container": "webm_dash", "language": null, "http_headers": {"Accept-Charset": "ISO-8859-1,utf-8;q=0.7,*;q=0.7", "Accept-Language": "en-us,en;q=0.5", "Accept-Encoding": "gzip, deflate", "Accept": "text/html,application/xhtml+xml,application/xml;q=0.9,*/*;q=0.8", "User-Agent": "Mozilla/5.0 (X11; Linux x86_64; rv:59.0) Gecko/20100101 Firefox/59.0"}, "url": "https://manifest.googlevideo.com/api/manifest/dash/requiressl/yes/source/youtube/id/777915536295e044/itag/0/ei/7aXRXOWnD4mtkgat0ZzwCg/playback_host/r4---sn-a5ms7n7e.googlevideo.com/mm/31%2C26/mn/sn-a5ms7n7e%2Csn-9gv7lnez/ms/au%2Conr/mv/u/pl/21/hfr/all/as/fmp4_audio_clear%2Cwebm_audio_clear%2Cwebm2_audio_clear%2Cfmp4_sd_hd_clear%2Cwebm2_sd_hd_clear/mt/1557242993/fvip/4/ip/155.94.169.201/ipbits/0/expire/1557264973/sparams/ip%2Cipbits%2Cexpire%2Crequiressl%2Csource%2Cid%2Citag%2Cei%2Cplayback_host%2Cmm%2Cmn%2Cms%2Cmv%2Cpl%2Chfr%2Cas/signature/91A46A312F589A77C88E876645AE6A23EB1377B9.9030732EC6AD9C6659B25009A8423C74F9C30BB4/key/yt8", "vcodec": "vp9", "width": 1280, "ext": "webm", "fragment_base_url": "https://r4---sn-a5ms7n7e.googlevideo.com/videoplayback/id/777915536295e044/itag/247/source/youtube/requiressl/yes/ei/7aXRXOWnD4mtkgat0ZzwCg/mm/31,26/mn/sn-a5ms7n7e,sn-9gv7lnez/ms/au,onr/mv/u/pl/21/ratebypass/yes/mime/video%2Fwebm/otfp/1/gir/yes/clen/81679046/lmt/1520585146929239/dur/457.657/mt/1557242993/fvip/4/disable_polymer/true/ip/155.94.169.201/ipbits/0/expire/1557264973/sparams/ip,ipbits,expire,id,itag,source,requiressl,ei,mm,mn,ms,mv,pl,ratebypass,mime,otfp,gir,clen,lmt,dur/signature/41D606AF50F22B8DD9B103D8CA7F8B4A44255396.23FBDE39D179A69798A68150197978B43865B308/key/dg_yt0/", "filesize": null, "fps": 30, "fragments": [{"path": "range/0-219"}, {"duration": 5.339, "path": "range/1741-1013646"}, {"duration": 5.338, "path": "range/1013647-1823262"}, {"duration": 5.339, "path": "range/1823263-2816579"}, {"duration": 5.339, "path": "range/2816580-3822125"}, {"duration": 5.338, "path": "range/3822126-4819701"}, {"duration": 5.339, "path": "range/4819702-5828612"}, {"duration": 5.339, "path": "range/5828613-6824529"}, {"duration": 5.338, "path": "range/6824530-7823876"}, {"duration": 5.339, "path": "range/7823877-8822967"}, {"duration": 5.339, "path": "range/8822968-9815305"}, {"duration": 5.338, "path": "range/9815306-10803523"}, {"duration": 5.339, "path": "range/10803524-11826551"}, {"duration": 5.339, "path": "range/11826552-12799024"}, {"duration": 5.338, "path": "range/12799025-13803477"}, {"duration": 5.339, "path": "range/13803478-14741119"}, {"duration": 5.339, "path": "range/14741120-15738273"}, {"duration": 5.338, "path": "range/15738274-16738120"}, {"duration": 5.339, "path": "range/16738121-17720236"}, {"duration": 5.339, "path": "range/17720237-18653425"}, {"duration": 5.338, "path": "range/18653426-19605761"}, {"duration": 5.339, "path": "range/19605762-20443874"}, {"duration": 5.339, "path": "range/20443875-21428781"}, {"duration": 5.338, "path": "range/21428782-22333831"}, {"duration": 5.339, "path": "range/22333832-23213860"}, {"duration": 5.339, "path": "range/23213861-23854060"}, {"duration": 5.338, "path": "range/23854061-24836938"}, {"duration": 5.339, "path": "range/24836939-25643553"}, {"duration": 5.339, "path": "range/25643554-26358366"}, {"duration": 5.338, "path": "range/26358367-27203291"}, {"duration": 5.339, "path": "range/27203292-27909122"}, {"duration": 5.339, "path": "range/27909123-28642873"}, {"duration": 5.338, "path": "range/28642874-29494288"}, {"duration": 5.339, "path": "range/29494289-30111053"}, {"duration": 5.339, "path": "range/30111054-30838073"}, {"duration": 5.338, "path": "range/30838074-31793579"}, {"duration": 5.339, "path": "range/31793580-32494072"}, {"duration": 5.339, "path": "range/32494073-33184224"}, {"duration": 5.338, "path": "range/33184225-33901123"}, {"duration": 5.339, "path": "range/33901124-34896527"}, {"duration": 5.339, "path": "range/34896528-35894465"}, {"duration": 5.338, "path": "range/35894466-36884055"}, {"duration": 5.339, "path": "range/36884056-37867204"}, {"duration": 5.339, "path": "range/37867205-38879408"}, {"duration": 5.338, "path": "range/38879409-39884928"}, {"duration": 5.339, "path": "range/39884929-40892183"}, {"duration": 5.339, "path": "range/40892184-41900330"}, {"duration": 5.338, "path": "range/41900331-42916328"}, {"duration": 5.339, "path": "range/42916329-43910927"}, {"duration": 5.339, "path": "range/43910928-44889067"}, {"duration": 5.338, "path": "range/44889068-45876574"}, {"duration": 5.339, "path": "range/45876575-46858565"}, {"duration": 5.339, "path": "range/46858566-47840358"}, {"duration": 5.338, "path": "range/47840359-48838321"}, {"duration": 5.339, "path": "range/48838322-49849209"}, {"duration": 5.339, "path": "range/49849210-50858955"}, {"duration": 5.338, "path": "range/50858956-51876645"}, {"duration": 5.339, "path": "range/51876646-52888083"}, {"duration": 5.339, "path": "range/52888084-53893470"}, {"duration": 5.338, "path": "range/53893471-54903384"}, {"duration": 5.339, "path": "range/54903385-55895509"}, {"duration": 5.339, "path": "range/55895510-56900303"}, {"duration": 5.338, "path": "range/56900304-57935783"}, {"duration": 5.339, "path": "range/57935784-58944842"}, {"duration": 5.339, "path": "range/58944843-59937951"}, {"duration": 5.338, "path": "range/59937952-60949635"}, {"duration": 5.339, "path": "range/60949636-61959859"}, {"duration": 5.339, "path": "range/61959860-62971762"}, {"duration": 5.338, "path": "range/62971763-63968298"}, {"duration": 5.339, "path": "range/63968299-64976433"}, {"duration": 5.339, "path": "range/64976434-65977237"}, {"duration": 5.338, "path": "range/65977238-66982533"}, {"duration": 5.339, "path": "range/66982534-67976855"}, {"duration": 5.339, "path": "range/67976856-68952754"}, {"duration": 5.338, "path": "range/68952755-69951375"}, {"duration": 5.339, "path": "range/69951376-70957587"}, {"duration": 5.339, "path": "range/70957588-71963347"}, {"duration": 5.338, "path": "range/71963348-72966856"}, {"duration": 5.339, "path": "range/72966857-73975440"}, {"duration": 5.339, "path": "range/73975441-74980692"}, {"duration": 5.338, "path": "range/74980693-75985857"}, {"duration": 5.339, "path": "range/75985858-76991084"}, {"duration": 5.339, "path": "range/76991085-77987186"}, {"duration": 5.338, "path": "range/77987187-78991927"}, {"duration": 5.339, "path": "range/78991928-79962439"}, {"duration": 5.339, "path": "range/79962440-80961504"}, {"duration": 3.87, "path": "range/80961505-81679045"}], "acodec": "none"}, {"asr": null, "tbr": 2334.558, "protocol": "http_dash_segments", "format": "136 - 1280x720 (DASH video)", "format_note": "DASH video", "height": 720, "manifest_url": "https://manifest.googlevideo.com/api/manifest/dash/requiressl/yes/source/youtube/id/777915536295e044/itag/0/ei/7aXRXOWnD4mtkgat0ZzwCg/playback_host/r4---sn-a5ms7n7e.googlevideo.com/mm/31%2C26/mn/sn-a5ms7n7e%2Csn-9gv7lnez/ms/au%2Conr/mv/u/pl/21/hfr/all/as/fmp4_audio_clear%2Cwebm_audio_clear%2Cwebm2_audio_clear%2Cfmp4_sd_hd_clear%2Cwebm2_sd_hd_clear/mt/1557242993/fvip/4/ip/155.94.169.201/ipbits/0/expire/1557264973/sparams/ip%2Cipbits%2Cexpire%2Crequiressl%2Csource%2Cid%2Citag%2Cei%2Cplayback_host%2Cmm%2Cmn%2Cms%2Cmv%2Cpl%2Chfr%2Cas/signature/91A46A312F589A77C88E876645AE6A23EB1377B9.9030732EC6AD9C6659B25009A8423C74F9C30BB4/key/yt8", "format_id": "136", "container": "mp4_dash", "language": null, "http_headers": {"Accept-Charset": "ISO-8859-1,utf-8;q=0.7,*;q=0.7", "Accept-Language": "en-us,en;q=0.5", "Accept-Encoding": "gzip, deflate", "Accept": "text/html,application/xhtml+xml,application/xml;q=0.9,*/*;q=0.8", "User-Agent": "Mozilla/5.0 (X11; Linux x86_64; rv:59.0) Gecko/20100101 Firefox/59.0"}, "url": "https://manifest.googlevideo.com/api/manifest/dash/requiressl/yes/source/youtube/id/777915536295e044/itag/0/ei/7aXRXOWnD4mtkgat0ZzwCg/playback_host/r4---sn-a5ms7n7e.googlevideo.com/mm/31%2C26/mn/sn-a5ms7n7e%2Csn-9gv7lnez/ms/au%2Conr/mv/u/pl/21/hfr/all/as/fmp4_audio_clear%2Cwebm_audio_clear%2Cwebm2_audio_clear%2Cfmp4_sd_hd_clear%2Cwebm2_sd_hd_clear/mt/1557242993/fvip/4/ip/155.94.169.201/ipbits/0/expire/1557264973/sparams/ip%2Cipbits%2Cexpire%2Crequiressl%2Csource%2Cid%2Citag%2Cei%2Cplayback_host%2Cmm%2Cmn%2Cms%2Cmv%2Cpl%2Chfr%2Cas/signature/91A46A312F589A77C88E876645AE6A23EB1377B9.9030732EC6AD9C6659B25009A8423C74F9C30BB4/key/yt8", "vcodec": "avc1.4d401f", "width": 1280, "ext": "mp4", "fragment_base_url": "https://r4---sn-a5ms7n7e.googlevideo.com/videoplayback/id/777915536295e044/itag/136/source/youtube/requiressl/yes/ei/7aXRXOWnD4mtkgat0ZzwCg/mm/31,26/mn/sn-a5ms7n7e,sn-9gv7lnez/ms/au,onr/mv/u/pl/21/ratebypass/yes/mime/video%2Fmp4/otfp/1/gir/yes/clen/115306718/lmt/1520524473015680/dur/457.657/mt/1557242993/fvip/4/disable_polymer/true/ip/155.94.169.201/ipbits/0/expire/1557264973/sparams/ip,ipbits,expire,id,itag,source,requiressl,ei,mm,mn,ms,mv,pl,ratebypass,mime,otfp,gir,clen,lmt,dur/signature/532F4BAA6D17A47DDA1421B58B31F5186739400E.579100E126A82086D2B5AA25DD3CA71C74AB7591/key/dg_yt0/", "filesize": null, "fps": 30, "fragments": [{"path": "range/0-712"}, {"duration": 5.339, "path": "range/1777-1546225"}, {"duration": 5.338, "path": "range/1546226-3096805"}, {"duration": 5.339, "path": "range/3096806-4638456"}, {"duration": 5.339, "path": "range/4638457-6188446"}, {"duration": 5.338, "path": "range/6188447-7738303"}, {"duration": 5.339, "path": "range/7738304-9228243"}, {"duration": 5.339, "path": "range/9228244-10775808"}, {"duration": 5.338, "path": "range/10775809-12322725"}, {"duration": 5.339, "path": "range/12322726-13872022"}, {"duration": 5.339, "path": "range/13872023-15147779"}, {"duration": 5.338, "path": "range/15147780-16501332"}, {"duration": 5.339, "path": "range/16501333-18050123"}, {"duration": 5.339, "path": "range/18050124-19599227"}, {"duration": 5.338, "path": "range/19599228-20989845"}, {"duration": 5.339, "path": "range/20989846-22121917"}, {"duration": 5.339, "path": "range/22121918-23417643"}, {"duration": 5.338, "path": "range/23417644-24794355"}, {"duration": 5.339, "path": "range/24794356-26345291"}, {"duration": 5.339, "path": "range/26345292-27503033"}, {"duration": 5.338, "path": "range/27503034-28643643"}, {"duration": 5.339, "path": "range/28643644-29619808"}, {"duration": 5.339, "path": "range/29619809-30877808"}, {"duration": 5.338, "path": "range/30877809-32032268"}, {"duration": 5.339, "path": "range/32032269-33013172"}, {"duration": 5.339, "path": "range/33013173-33846540"}, {"duration": 5.338, "path": "range/33846541-34934723"}, {"duration": 5.339, "path": "range/34934724-35876007"}, {"duration": 5.339, "path": "range/35876008-36694264"}, {"duration": 5.338, "path": "range/36694265-37599427"}, {"duration": 5.339, "path": "range/37599428-38426657"}, {"duration": 5.339, "path": "range/38426658-39211663"}, {"duration": 5.338, "path": "range/39211664-40085815"}, {"duration": 5.339, "path": "range/40085816-40940382"}, {"duration": 5.339, "path": "range/40940383-41805771"}, {"duration": 5.338, "path": "range/41805772-43048453"}, {"duration": 5.339, "path": "range/43048454-43878831"}, {"duration": 5.339, "path": "range/43878832-44698508"}, {"duration": 5.338, "path": "range/44698509-45541692"}, {"duration": 5.339, "path": "range/45541693-47087729"}, {"duration": 5.339, "path": "range/47087730-48636565"}, {"duration": 5.338, "path": "range/48636566-50194591"}, {"duration": 5.339, "path": "range/50194592-51466271"}, {"duration": 5.339, "path": "range/51466272-52960404"}, {"duration": 5.338, "path": "range/52960405-54503518"}, {"duration": 5.339, "path": "range/54503519-56053376"}, {"duration": 5.339, "path": "range/56053377-57600949"}, {"duration": 5.338, "path": "range/57600950-59149687"}, {"duration": 5.339, "path": "range/59149688-60645868"}, {"duration": 5.339, "path": "range/60645869-61670126"}, {"duration": 5.338, "path": "range/61670127-62786018"}, {"duration": 5.339, "path": "range/62786019-63915348"}, {"duration": 5.339, "path": "range/63915349-64892452"}, {"duration": 5.338, "path": "range/64892453-66150743"}, {"duration": 5.339, "path": "range/66150744-67523910"}, {"duration": 5.339, "path": "range/67523911-68983888"}, {"duration": 5.338, "path": "range/68983889-70538865"}, {"duration": 5.339, "path": "range/70538866-71985957"}, {"duration": 5.339, "path": "range/71985958-73275486"}, {"duration": 5.338, "path": "range/73275487-74666139"}, {"duration": 5.339, "path": "range/74666140-75883826"}, {"duration": 5.339, "path": "range/75883827-77434975"}, {"duration": 5.338, "path": "range/77434976-78988330"}, {"duration": 5.339, "path": "range/78988331-80541860"}, {"duration": 5.339, "path": "range/80541861-82097832"}, {"duration": 5.338, "path": "range/82097833-83649496"}, {"duration": 5.339, "path": "range/83649497-85199038"}, {"duration": 5.339, "path": "range/85199039-86749147"}, {"duration": 5.338, "path": "range/86749148-88301319"}, {"duration": 5.339, "path": "range/88301320-89846876"}, {"duration": 5.339, "path": "range/89846877-91395769"}, {"duration": 5.338, "path": "range/91395770-92944738"}, {"duration": 5.339, "path": "range/92944739-94487990"}, {"duration": 5.339, "path": "range/94487991-96037098"}, {"duration": 5.338, "path": "range/96037099-97589668"}, {"duration": 5.339, "path": "range/97589669-98913702"}, {"duration": 5.339, "path": "range/98913703-100383798"}, {"duration": 5.338, "path": "range/100383799-101931738"}, {"duration": 5.339, "path": "range/101931739-103480223"}, {"duration": 5.339, "path": "range/103480224-105029306"}, {"duration": 5.338, "path": "range/105029307-106579393"}, {"duration": 5.339, "path": "range/106579394-108126356"}, {"duration": 5.339, "path": "range/108126357-109542522"}, {"duration": 5.338, "path": "range/109542523-111090792"}, {"duration": 5.339, "path": "range/111090793-112637158"}, {"duration": 5.339, "path": "range/112637159-114183946"}, {"duration": 3.871, "path": "range/114183947-115306717"}], "acodec": "none"}, {"http_headers": {"Accept-Charset": "ISO-8859-1,utf-8;q=0.7,*;q=0.7", "Accept-Language": "en-us,en;q=0.5", "Accept-Encoding": "gzip, deflate", "Accept": "text/html,application/xhtml+xml,application/xml;q=0.9,*/*;q=0.8", "User-Agent": "Mozilla/5.0 (X11; Linux x86_64; rv:59.0) Gecko/20100101 Firefox/59.0"}, "protocol": "https", "format": "18 - 640x360 (medium)", "url": "https://r4---sn-a5ms7n7e.googlevideo.com/videoplayback?id=o-AG0jVc-rfTTRGDs6PsyWKMZlfWEnnSB7-2rjhSx-WiHg&itag=18&source=youtube&requiressl=yes&mm=31%2C26&mn=sn-a5ms7n7e%2Csn-9gv7lnez&ms=au%2Conr&mv=u&pl=21&ei=7aXRXOWnD4mtkgat0ZzwCg&mime=video%2Fmp4&gir=yes&clen=38864568&ratebypass=yes&dur=457.711&lmt=1518534144782818&mt=1557242993&fvip=4&c=WEB&ip=155.94.169.201&ipbits=0&expire=1557264973&sparams=ip%2Cipbits%2Cexpire%2Cid%2Citag%2Csource%2Crequiressl%2Cmm%2Cmn%2Cms%2Cmv%2Cpl%2Cei%2Cmime%2Cgir%2Cclen%2Cratebypass%2Cdur%2Clmt&signature=89C38E1F138295525E8B665BA1AA362D402060CA.8B6774FC94EA328CDE518ABB7DE54972E6126630&key=yt8", "quality": 1, "vcodec": "avc1.42001E", "format_note": "medium", "ext": "mp4", "player_url": "/yts/jsbin/player_ias-vflisCO7O/en_US/base.js", "width": 640, "abr": 96, "filesize": 38864568, "format_id": "18", "height": 360, "resolution": "640x360", "acodec": "mp4a.40.2"}, {"http_headers": {"Accept-Charset": "ISO-8859-1,utf-8;q=0.7,*;q=0.7", "Accept-Language": "en-us,en;q=0.5", "Accept-Encoding": "gzip, deflate", "Accept": "text/html,application/xhtml+xml,application/xml;q=0.9,*/*;q=0.8", "User-Agent": "Mozilla/5.0 (X11; Linux x86_64; rv:59.0) Gecko/20100101 Firefox/59.0"}, "protocol": "https", "format": "43 - 640x360 (medium)", "url": "https://r4---sn-a5ms7n7e.googlevideo.com/videoplayback?id=o-AG0jVc-rfTTRGDs6PsyWKMZlfWEnnSB7-2rjhSx-WiHg&itag=43&source=youtube&requiressl=yes&mm=31%2C26&mn=sn-a5ms7n7e%2Csn-9gv7lnez&ms=au%2Conr&mv=u&pl=21&ei=7aXRXOWnD4mtkgat0ZzwCg&mime=video%2Fwebm&gir=yes&clen=48714362&ratebypass=yes&dur=0.000&lmt=1518536624002613&mt=1557242993&fvip=4&c=WEB&ip=155.94.169.201&ipbits=0&expire=1557264973&sparams=ip%2Cipbits%2Cexpire%2Cid%2Citag%2Csource%2Crequiressl%2Cmm%2Cmn%2Cms%2Cmv%2Cpl%2Cei%2Cmime%2Cgir%2Cclen%2Cratebypass%2Cdur%2Clmt&signature=36689AA72235989705CB7296BD071294452C97B6.E18B112F1DB79F62BF22F0352B0D89EA14ED2022&key=yt8", "quality": 1, "vcodec": "vp8.0", "format_note": "medium", "ext": "webm", "player_url": "/yts/jsbin/player_ias-vflisCO7O/en_US/base.js", "width": 640, "abr": 128, "filesize": 48714362, "format_id": "43", "height": 360, "resolution": "640x360", "acodec": "vorbis"}, {"http_headers": {"Accept-Charset": "ISO-8859-1,utf-8;q=0.7,*;q=0.7", "Accept-Language": "en-us,en;q=0.5", "Accept-Encoding": "gzip, deflate", "Accept": "text/html,application/xhtml+xml,application/xml;q=0.9,*/*;q=0.8", "User-Agent": "Mozilla/5.0 (X11; Linux x86_64; rv:59.0) Gecko/20100101 Firefox/59.0"}, "protocol": "https", "format": "22 - 1280x720 (hd720)", "url": "https://r4---sn-a5ms7n7e.googlevideo.com/videoplayback?id=o-AG0jVc-rfTTRGDs6PsyWKMZlfWEnnSB7-2rjhSx-WiHg&itag=22&source=youtube&requiressl=yes&mm=31%2C26&mn=sn-a5ms7n7e%2Csn-9gv7lnez&ms=au%2Conr&mv=u&pl=21&ei=7aXRXOWnD4mtkgat0ZzwCg&mime=video%2Fmp4&ratebypass=yes&dur=457.711&lmt=1520524666844752&mt=1557242993&fvip=4&c=WEB&ip=155.94.169.201&ipbits=0&expire=1557264973&sparams=ip%2Cipbits%2Cexpire%2Cid%2Citag%2Csource%2Crequiressl%2Cmm%2Cmn%2Cms%2Cmv%2Cpl%2Cei%2Cmime%2Cratebypass%2Cdur%2Clmt&signature=8028A2E7BA999D232D7AD6D67F1C807093974A42.536F2CB2CFFE7B2981FF74EA29F6CE1A982119DA&key=yt8", "quality": 2, "vcodec": "avc1.64001F", "format_note": "hd720", "ext": "mp4", "player_url": "/yts/jsbin/player_ias-vflisCO7O/en_US/base.js", "width": 1280, "abr": 192, "format_id": "22", "height": 720, "resolution": "1280x720", "acodec": "mp4a.40.2"}], "playlist_uploader_id": "UCheuDxi3s2WAefGCbLHwqAw", "channel_url": null, "resolution": null, "width": 256, "n_entries": 227, "age_limit": 0}